{"TUBA1B": 0, "HLA-B": 0, "RSPO4": 0, "TRIM16L": 0, "IL9R": 0, "IL4R": 0, "MIP": 0, "PRMT8": 0, "FANCI": 0, "PECAM1": 0, "CAMK1D": 0, "PAX6": 0, "SH2B3": 0, "LMO1": 0, "GCM1": 0, "SIAH1": 0, "EPOR": 0, "TP53BP2": 0, "Q53SB5": 0, "GORASP1": 0, "FEN1": 0, "UBA1": 0, "ELAVL1": 0, "PTX3": 0, "LHX1": 0, "DNMT3A": 0, "E9PFZ0": 0, "TYMS": 0, "RPL11": 0, "IRAK1BP1": 0, "EPAS1": 0, "HDAC4": 1, "SMC3": 1, "PPP1CA": 1, "K9JA46": 1, "IL16": 1, "ADAM19": 1, "FGFR3": 1, "DDC": 1, "ADRBK2": 1, "LCAT": 1, "PRKG1": 1, "CRYAB": 1, "DLG3": 1, "PHPT1": 1, "SARG": 1, "ELK3": 1, "DAP3": 1, "ATP1A1": 1, "PITPNA": 1, "UBE2T": 1, "OGG1": 1, "MOB1A": 1, "RAD51C": 1, "Q8IZZ5": 1, "LY86": 1, "FLT1": 1, "ULK2": 1, "TRPM7": 1, "EFNA4": 1, "PADI3": 1, "CDK3": 1, "HIF1AN": 1, "PTPN13": 1, "CEBPB": 1, "SYVN1": 1, "FOXK2": 1, "KAT2A": 1, "IL10": 1, "HMGCR": 2, "FZD2": 2, "JUN": 2, "EGLN2": 2, "FZD8": 2, "HSPA8": 2, "PDZK1": 2, "PTBP1": 2, "ATF3": 2, "EDNRA": 2, "MAP3K3": 2, "CXCL3": 2, "BCKDHA": 2, "RXRA": 2, "CDC42": 2, "EFNA5": 2, "HBEGF": 2, "TROAP": 2, "CPSF3": 2, "TIGAR": 2, "ITPKA": 2, "TBKBP1": 2, "PI4K2A": 2, "SOS1": 2, "GAS1": 2, "CD4": 2, "CYP3A4": 2, "PYDC1": 2, "RGS19": 2, "KDM7A": 2, "RNF146": 2, "ROBO4": 2, "ADAM2": 2, "PLG": 2, "S100A7": 3, "PACS1": 3, "AKR1B1": 3, "FAM107A": 3, "CUL2": 3, "PVRL4": 3, "ATF1": 3, "UBE2N": 3, "SIGLEC9": 3, "MUS81": 3, "APBA1": 3, "PTCH2": 3, "PELI3": 3, "B4DHI4": 3, "DDX58": 3, "TGFB3": 3, "SPRY1": 3, "XK": 3, "TCEB1": 3, "Q547U9": 3, "CAMLG": 4, "LINGO1": 4, "PRTN3": 4, "NFYC": 4, "MAML2": 4, "CTNND1": 4, "TF": 4, "CIC": 4, "LEPR": 4, "GABARAPL3": 4, "F2RL2": 4, "UBTF": 4, "PRKAA2": 4, "EIF2AK4": 4, "MATK": 4, "TUBA4B": 4, "PHF11": 4, "BMPR2": 4, "OSGIN1": 4, "KLK3": 4, "ARF1": 4, "KALRN": 4, "MAP3K11": 4, "ACVRL1": 4, "MEX3A": 4, "CD6": 4, "LHCGR": 4, "PIK3C2A": 4, "CYBB": 4, "PCGF6": 4, "YAP1": 4, "FIGF": 4, "IFNL3": 4, "B4DG68": 5, "DISP2": 5, "NFE2": 5, "EXOC2": 5, "KCNN4": 5, "CABLES1": 5, "SLC2A2": 5, "SYN3": 5, "MAT1A": 5, "CHUK": 5, "ICAM1": 5, "PIK3R4": 5, "TNFRSF10D": 5, "LRP1": 5, "PKD1": 5, "S100A9": 5, "LIN9": 5, "ARHGEF12": 5, "DCLRE1C": 5, "MYL6B": 5, "HOXB9": 5, "A8K341": 5, "ARHGAP32": 5, "CCL25": 5, "SETDB2": 5, "CDC45": 5, "F2R": 5, "CTGF": 5, "CARD17": 5, "APH1A": 5, "ACTL6A": 5, "ABCG2": 5, "PIK3CB": 5, "TIAL1": 5, "TRPC7": 5, "COPS6": 5, "CDV3": 5, "CAMK4": 5, "WNK4": 5, "IL18": 5, "PEBP1": 5, "MEF2A": 5, "UHRF1": 6, "ANAPC10": 6, "TP53INP1": 6, "SYNJ1": 6, "CXCL6": 6, "KCNE3": 6, "POLD2": 6, "GEMIN2": 6, "SLC25A4": 6, "LIF": 6, "Q14025": 6, "TNFRSF13B": 6, "SOX6": 6, "MAP2K3": 6, "LYN": 6, "PABPC1": 6, "BUB1": 6, "NUTF2": 6, "CSN1S1": 6, "CASP8": 6, "HIST1H2AM": 6, "TELO2": 6, "AKT3": 6, "SETD7": 6, "CISD2": 6, "TJP3": 6, "FGF9": 6, "PRDX1": 6, "ATR": 6, "PIN1": 6, "IKBKB": 6, "SETD6": 6, "IFNL1": 6, "MYO18A": 6, "FGFR1": 6, "MAP3K9": 6, "CKAP4": 6, "PROK1": 6, "HCRTR1": 6, "BMP4": 7, "CDK8": 7, "MST1R": 7, "RHOB": 7, "PTP4A1": 7, "FADD": 7, "SCAMP1": 7, "IL15": 7, "EGF": 7, "REL": 7, "LAMA4": 7, "SCRIB": 7, "RPS3": 7, "CD72": 7, "ITGA3": 7, "CTNNB1": 7, "PCNT": 7, "ATP2C1": 7, "RND3": 7, "AXIN1": 7, "QTRT1": 7, "CD63": 7, "PPP1R3A": 7, "PPP2R5B": 7, "ATXN1": 7, "PIAS1": 8, "PDK2": 8, "TGFA": 8, "TJP2": 8, "WNT11": 8, "GAL": 8, "ITPR3": 8, "RAPGEF6": 8, "KDM4B": 8, "PIM3": 8, "SH3BP4": 8, "RPSA": 8, "ZDHHC2": 8, "MMP7": 8, "TOM1L1": 8, "SLC30A9": 8, "DUSP9": 8, "CDX2": 8, "IL23A": 8, "SMN2": 8, "SPRED1": 8, "GRAP2": 8, "CAND1": 8, "AMOT": 8, "PLAGL2": 8, "PIK3R2": 8, "NFKBIB": 9, "PPP1R14B": 9, "PHF20": 9, "SMG8": 9, "YWHAG": 9, "STAT6": 9, "FAM102A": 9, "DNMT3B": 9, "XXYLT1": 9, "AIRE": 9, "AVP": 9, "LAMC2": 9, "CYP3A5": 9, "TFAP4": 9, "RSPO1": 9, "PLK1": 9, "ORC1": 9, "SEC14L2": 9, "PPP3CA": 9, "PDE6G": 9, "ESPL1": 9, "FASN": 9, "MYOG": 9, "EFNB1": 9, "GNA13": 9, "SMARCAD1": 9, "RPS19": 9, "STEAP4": 9, "RASGEF1C": 9, "PACSIN3": 9, "ELF1": 10, "NFKB2": 10, "ECHS1": 10, "WWP1": 10, "COPS3": 10, "BAG6": 10, "DEFB106A": 10, "TCP10L": 10, "HR": 10, "CDKN2C": 10, "SHC2": 10, "CXCR4": 10, "RASGRP1": 10, "CTPS2": 10, "MET": 10, "PPP1CC": 10, "SETDB1": 10, "MAP2K7": 10, "PTMA": 10, "NDP": 10, "SOCS4": 10, "PAIP2": 10, "PDGFA": 10, "CDK5R1": 11, "C6": 11, "PTPRJ": 11, "SNAI2": 11, "HTATIP2": 11, "FLII": 11, "A8K503": 11, "V9HWA6": 11, "L1CAM": 11, "PSMC5": 11, "ATXN3": 11, "WIPI1": 11, "NFIA": 11, "SMAD4": 11, "NOS1": 11, "MECOM": 11, "PCYT1A": 11, "LATS1": 11, "ZNF420": 11, "RRAGD": 11, "PJA1": 11, "POLL": 11, "RARA": 11, "SNCB": 11, "IL3": 11, "CRIP2": 11, "BCCIP": 11, "TBR1": 11, "PIAS4": 11, "CROCC": 11, "MED12": 11, "IGHE": 11, "EIF2S1": 11, "GMCL1": 11, "Q659G9": 11, "MRE11A": 11, "LMNB2": 11, "PPP1R1A": 11, "KIT": 11, "MDC1": 11, "CDKN1C": 11, "TP73": 11, "CSN2": 11, "ASCL1": 11, "UCHL5": 11, "NUP210": 11, "LCK": 11, "BDKRB1": 11, "CAMK2B": 12, "SIGLEC7": 12, "MEF2D": 12, "B7Z1Q3": 12, "TAF9": 12, "PMAIP1": 12, "NEDD4": 12, "OPTN": 12, "NPHS2": 12, "TNFRSF10A": 12, "FOXP3": 12, "CDK5RAP2": 12, "AIM2": 12, "AHNAK": 12, "Q59HH7": 12, "TGFBR2": 12, "TPPP": 12, "PDE3B": 12, "CEACAM1": 12, "DRD3": 12, "JUND": 12, "BNIP2": 12, "STAT1": 12, "PHB2": 12, "ICAM4": 12, "HNRNPC": 12, "ZDHHC16": 12, "PDZD3": 12, "PIAS2": 12, "PPM1A": 12, "ESCO1": 12, "EDNRB": 12, "SHOC2": 12, "LPAR1": 12, "FBLN2": 12, "USO1": 12, "ZFAND5": 12, "SNRK": 12, "GP1BA": 12, "INVS": 13, "MYB": 13, "ATM": 13, "GNAT2": 13, "GRK6": 13, "TTI1": 13, "TUBA4A": 13, "MAPK8IP3": 13, "CTSL": 13, "DPP4": 13, "PRKCZ": 13, "SHFM1": 13, "G6PD": 13, "EPS15L1": 13, "CAMP": 13, "UBASH3B": 13, "E2F5": 13, "SSTR1": 13, "V9HWE1": 13, "BANF1": 13, "ADRA1A": 13, "AMER1": 13, "KLF12": 13, "PPP1CB": 13, "C2": 13, "MAPK1": 13, "PAX3": 13, "IL23R": 13, "RORA": 13, "VAMP7": 13, "RGS14": 13, "GLP2R": 13, "PLEKHG6": 13, "HOMER3": 13, "PRR5L": 13, "DENND3": 13, "HIST1H1E": 13, "PKN1": 13, "PTGER1": 13, "KREMEN2": 13, "EVI5": 13, "ORM1": 13, "URI1": 13, "AVEN": 13, "EIF1AX": 13, "CHRNA7": 13, "IFNGR2": 14, "TRIM38": 14, "ADCY3": 14, "HAVCR2": 14, "KDR": 14, "HIP1": 14, "CABP2": 14, "TNFSF10": 14, "UBE4B": 14, "PSEN1": 14, "APEX1": 14, "SH3RF1": 14, "COPS8": 14, "PHLPP2": 14, "NRK": 14, "MAPK8IP1": 14, "PPP1R13B": 14, "BCL10": 14, "NCAPG": 14, "GBX2": 14, "RGS16": 14, "MCHR1": 14, "NANOG": 14, "SPHK1": 14, "OPRD1": 14, "RAF1": 14, "HIF3A": 14, "PRPF4B": 14, "Q9HA84": 14, "FKBP8": 14, "ACD": 14, "UHMK1": 14, "MAP1LC3B": 14, "CRK": 14, "TRAP1": 14, "PSMD1": 14, "PRIM2": 14, "NF1": 14, "KDM5A": 14, "KLKB1": 14, "GZMM": 14, "POLR1B": 15, "PFKL": 15, "ASAH2B": 15, "BCL3": 15, "ASF1B": 15, "CD44": 15, "CAMK2A": 15, "BACE2": 15, "AHR": 15, "PER1": 15, "DBNL": 15, "BGN": 15, "CCL14": 15, "TUBB3": 16, "AIFM2": 16, "TFAM": 16, "PCNA": 16, "RHOT1": 16, "NRTN": 16, "TNFRSF12A": 16, "TICRR": 16, "IFNGR1": 16, "CCT2": 16, "SMAD9": 16, "SAMHD1": 16, "PFKFB1": 16, "MAP3K13": 16, "GALR3": 16, "SST": 16, "ADM": 16, "HOXC10": 16, "LPAR6": 16, "LRIG1": 17, "ARID4A": 17, "BNC1": 17, "EPHA3": 17, "TTC1": 17, "PRKCG": 17, "CTDSP1": 17, "KRT36": 17, "CRTC1": 17, "RPL5": 17, "KIR2DL1": 17, "KIAA0226": 17, "NFAT5": 17, "WNT10A": 17, "MCM3AP": 17, "TFDP2": 17, "CSNK1D": 17, "DUSP3": 17, "HAT1": 17, "ALK": 17, "SERBP1": 17, "GAB3": 17, "PRDX6": 17, "LCP1": 17, "PPP1R9B": 17, "CEBPA": 17, "AMPH": 17, "PRKACB": 17, "ANGPTL4": 17, "POU3F1": 17, "DNAJC3": 17, "CCL15": 17, "SAV1": 17, "LIPE": 17, "MIB2": 17, "ATAD3B": 17, "VRK2": 17, "METTL1": 17, "JAK1": 17, "CSF2": 17, "CD81": 17, "FCGR1A": 17, "NR4A3": 17, "SOX10": 17, "POLR2B": 17, "KRT20": 17, "KIFAP3": 18, "NIFK": 18, "HLA-DRA": 18, "CXCL10": 18, "PRDM16": 18, "RPS6KA2": 18, "DSN1": 18, "STOM": 18, "CAMKK2": 18, "NR4A1": 18, "PPP2R5C": 18, "GCG": 18, "FANCD2": 18, "PACSIN2": 18, "STAMBP": 18, "POLA2": 18, "LAMB2": 18, "IL11": 18, "GPR75": 18, "KCNJ2": 19, "Q4LE70": 19, "SHANK1": 19, "PLD2": 19, "PKD2": 19, "RHOQ": 19, "SOCS1": 19, "KCNJ11": 19, "SSRP1": 19, "JAG2": 19, "FGF3": 19, "NQO1": 19, "FRS2": 19, "RHEB": 19, "COPS4": 19, "HHEX": 19, "HGS": 19, "EPHB6": 19, "SRPK2": 19, "ODF2": 19, "ATG14": 19, "E2F1": 19, "RRAS": 19, "STARD10": 19, "ITGAL": 19, "EXOC7": 19, "HIST2H2BF": 19, "NONO": 19, "STATH": 19, "NLRP2": 19, "SEPT1": 19, "DHX33": 19, "DEK": 19, "HIST2H2AC": 19, "HES5": 19, "CCDC50": 19, "Q9P084": 19, "KIF4A": 19, "PRSS23": 19, "TNFSF15": 19, "RCOR1": 19, "SEPT9": 19, "ROBO1": 19, "ERCC1": 19, "EDA2R": 19, "TERF1": 19, "GNL3": 20, "EHMT1": 20, "ATXN2": 20, "ARPC4": 20, "PTPN9": 20, "A8K379": 20, "TSKU": 20, "FBXW5": 20, "ACTA1": 20, "SLC12A2": 20, "NRG3": 20, "TPBG": 20, "PAX2": 20, "CTNNA1": 20, "PNCK": 20, "MOK": 20, "GABRB2": 20, "ERN1": 20, "LIPH": 20, "PER2": 20, "CDK7": 20, "COPS2": 20, "Q96BA7": 20, "UBE2D3": 20, "YWHAB": 20, "IL1RAP": 20, "ATG4A": 20, "DLL4": 20, "CABP1": 20, "MGST1": 20, "PDC": 20, "MED6": 20, "SMURF1": 20, "RASGEF1B": 20, "CACNG2": 20, "IGFBP5": 20, "NCF2": 20, "NUDC": 20, "PTPRE": 20, "TRPV1": 20, "NR1I3": 20, "TMOD1": 20, "ASH2L": 20, "CD40": 20, "RAB3A": 20, "PYGM": 21, "EPHB2": 21, "RBSN": 21, "SETMAR": 21, "SKI": 21, "MAP4K5": 21, "TRAF6": 21, "ZNF622": 21, "ACTN1": 21, "KIF13B": 21, "TOPORS": 21, "SESTD1": 21, "FUBP1": 21, "SLU7": 21, "CCR9": 21, "PPM1E": 21, "ATG13": 21, "SRXN1": 21, "CCL11": 21, "B2RBL9": 21, "FOXG1": 21, "CR2": 21, "S1PR2": 21, "CD19": 21, "HOXA10": 21, "CDK11A": 21, "EPN1": 21, "FBLN1": 21, "CLIP3": 21, "SH3GL1": 21, "KIRREL": 21, "CLDN3": 21, "B4DW78": 22, "MAGI2": 22, "MCTS1": 22, "DDX3X": 22, "UBE2A": 22, "INCA1": 22, "NR1D1": 22, "SAP18": 22, "CEP250": 22, "PTPN11": 22, "UBE2S": 22, "KISS1": 22, "FHL5": 22, "SERPINC1": 22, "CBR3": 22, "PDK3": 22, "EIF4B": 22, "CACNA1H": 22, "CFLAR": 22, "GHRL": 22, "KLHL25": 22, "TNFRSF10C": 22, "EIF1": 22, "CDC14B": 22, "PDE1C": 22, "BIK": 22, "STAT5B": 23, "TNFAIP3": 23, "KLHL11": 23, "PIP5K1C": 23, "ATXN10": 23, "MARK4": 23, "CCL19": 23, "ATG4D": 23, "MADD": 23, "ALPL": 23, "LBP": 23, "TP63": 23, "CSE1L": 23, "MXD4": 23, "IL2": 23, "TTBK2": 23, "NCBP2": 23, "MCOLN2": 23, "TPD52": 23, "PPP1R14C": 24, "CERK": 24, "TRPC5": 24, "DYRK1B": 24, "MYH2": 24, "SIGIRR": 24, "AKAP9": 24, "ADIPOR2": 24, "TBX21": 24, "FAM64A": 24, "SPTAN1": 24, "MLKL": 24, "YWHAZ": 24, "EYA3": 24, "MNAT1": 24, "DSTN": 24, "OAS2": 24, "CNTN6": 24, "GCKR": 24, "PCSK7": 24, "PRLR": 24, "ZDHHC9": 24, "CCKAR": 24, "ADRBK1": 24, "EIF3E": 24, "EEF1A1": 24, "TAF1A": 24, "TRPC6": 24, "PDCD1": 25, "MYBBP1A": 25, "TRPM4": 25, "ICOS": 25, "FAS": 25, "HPCA": 25, "HLA-DRB1": 25, "FSHB": 25, "Q59FX5": 25, "CFI": 25, "EDN2": 25, "KEAP1": 25, "ORC6": 25, "TOP3A": 25, "TRRAP": 25, "RPL10": 25, "LGALS3": 25, "TACC3": 26, "FBXW11": 26, "CCR1": 26, "TMBIM6": 26, "DCAF7": 26, "LTK": 26, "NUMB": 26, "PRPH": 26, "WNK2": 26, "JAG1": 26, "TRIO": 26, "VDR": 26, "GTF2H4": 26, "SOX17": 26, "ASAP3": 26, "KDM4D": 26, "RLF": 26, "CDH3": 26, "Q59GK3": 26, "ATP1B1": 26, "SERPINB9": 26, "CLTC": 26, "PKIA": 26, "YLPM1": 26, "EREG": 26, "KMT2D": 26, "DNM1": 26, "MELK": 26, "FKBP5": 26, "UBE3C": 26, "VAMP4": 26, "A0A024R7C1": 26, "SETD1B": 26, "IKBKAP": 26, "WWC1": 26, "PRKCI": 27, "PHF1": 27, "CDK1": 27, "SERPIND1": 27, "PRKX": 27, "EZH2": 27, "USP1": 27, "CENPF": 27, "MLH3": 27, "CUL4A": 27, "ERG": 27, "UXT": 27, "CYCS": 27, "NUP88": 27, "RAB5A": 27, "CD247": 27, "CDON": 27, "PBX3": 27, "PSMA3": 27, "ZFP91": 27, "GAS2": 27, "PTPN1": 27, "ITGAM": 27, "KRT5": 27, "BNIP3": 27, "ARHGEF19": 27, "CAPZB": 27, "UPF1": 27, "C1QBP": 27, "SLC22A18": 27, "RGS10": 27, "FHOD1": 27, "BCAR3": 27, "AIMP2": 27, "IL22RA1": 28, "DSG2": 28, "FAM175A": 28, "PDIA5": 28, "ACLY": 28, "COL3A1": 28, "HGF": 28, "MTOR": 28, "EWSR1": 28, "F9": 28, "AGO2": 28, "PIK3R1": 28, "SORBS1": 28, "CHMP4B": 28, "BIN1": 28, "CSF2RB": 28, "TAL2": 28, "DOK5": 28, "HMGB2": 28, "VHL": 28, "FBXW7": 28, "MT2A": 28, "NLRP1": 28, "NCOA6": 28, "FCRL3": 28, "HIRA": 28, "MSR1": 28, "MKL1": 28, "FAM129A": 28, "NR3C2": 28, "F2": 28, "TUBD1": 28, "FRAT1": 28, "CREBZF": 28, "NOS3": 28, "FOXO1": 29, "PDCD5": 29, "PLAU": 29, "PTPN3": 29, "PAX8": 29, "NSMCE2": 29, "V9HWC2": 29, "SERPINB4": 29, "KIF11": 29, "TFG": 29, "MTA1": 29, "PRL": 29, "TRIP11": 29, "CALCOCO2": 29, "WAS": 29, "KLF4": 29, "MAP3K10": 29, "PPP4C": 29, "LY96": 29, "BCAM": 29, "A8K8W7": 29, "CD9": 29, "SH2B2": 29, "WNT7A": 29, "PKD1L3": 29, "B3KTA3": 29, "ANLN": 29, "IGFBP4": 29, "CHAF1A": 29, "STIM1": 29, "DNER": 29, "RNF125": 29, "PDE7A": 29, "CTSG": 29, "NRG1": 29, "JDP2": 29, "PRKCH": 29, "TBX3": 29, "SHPRH": 30, "GZMA": 30, "MKI67": 30, "ZBTB4": 30, "OPRM1": 30, "RGS7": 30, "NRP2": 30, "VCP": 30, "RPS6KA5": 30, "GDNF": 30, "ORC5": 30, "NAB2": 30, "PTPN22": 30, "EPB41": 30, "RGL2": 30, "FOS": 30, "Q9UFY1": 30, "TAF4": 30, "PPBP": 30, "A9UF07": 30, "CALU": 30, "MED14": 30, "C9orf89": 30, "DOCK2": 30, "UBE2I": 30, "TOMM70A": 31, "DLGAP1": 31, "NCOA3": 31, "RIOK3": 31, "GLIS3": 31, "MED1": 31, "GATA2": 31, "NFATC1": 31, "DIAPH2": 31, "BUB1B": 31, "ARG1": 31, "S100A11": 31, "RIPK4": 31, "FGFR1OP": 31, "SPRY2": 31, "KHDRBS1": 31, "ITPR1": 31, "Q59FG2": 31, "CARD16": 31, "CXCL5": 31, "RAP1B": 31, "CRHR2": 31, "ARHGAP33": 31, "PIGR": 31, "HRK": 32, "TBC1D4": 32, "ELAVL4": 32, "IL17RD": 32, "CCL4": 32, "SMARCA2": 32, "ECSIT": 32, "ERAP1": 32, "HIC1": 32, "NME3": 32, "ACVR2B": 32, "RNF216": 32, "TYK2": 32, "HNF1B": 32, "SLC9A3R1": 32, "ENO1": 32, "ACAA2": 32, "RGS3": 32, "ACPT": 32, "MDM2": 32, "ZEB1": 32, "APLF": 32, "GUCY2C": 32, "PSMB5": 32, "KAT5": 32, "ITGA4": 32, "SMAD7": 32, "FGF8": 32, "YWHAE": 32, "DOK4": 32, "KRT14": 32, "ENPP2": 32, "NLGN1": 32, "PPP1R1B": 32, "CAPNS1": 32, "ETV1": 32, "SDCCAG8": 32, "TUBA1A": 33, "TEAD1": 33, "SFTPA1": 33, "CARD9": 33, "INPP5D": 33, "CCL27": 33, "BTK": 33, "TTN": 33, "SPIB": 33, "PTPRH": 33, "BAZ2A": 33, "Q9UG98": 33, "PLAA": 33, "RIOK2": 33, "MPRIP": 33, "DUSP10": 33, "F5": 33, "PTPN12": 33, "MCM4": 33, "DOT1L": 33, "IL21R": 33, "SLC4A1": 33, "DAP": 33, "CAD": 33, "B2RB33": 33, "RAP1GAP2": 33, "INSIG1": 33, "TBXA2R": 33, "DIABLO": 33, "POGLUT1": 33, "EIF4A3": 33, "SNX1": 33, "CSNK1G1": 33, "TUBA3C": 33, "MN1": 33, "CDK4": 33, "OBSCN": 34, "PPP1R8": 34, "DLG1": 34, "CENPQ": 34, "NDFIP1": 34, "RNF41": 34, "SGOL1": 34, "MSL2": 34, "PINX1": 34, "ERC1": 34, "FZD1": 34, "CLSPN": 34, "CREBBP": 34, "GPC3": 34, "RAD23A": 34, "HIF1A": 34, "CX3CL1": 34, "PDXP": 34, "CIRBP": 34, "SP2": 35, "SSH3": 35, "FBXO6": 35, "IL20RB": 35, "UCN3": 35, "LEP": 35, "CDT1": 35, "FGF17": 35, "GPM6A": 35, "ACTG1": 35, "CDKN2B": 35, "KIF20B": 35, "HSPG2": 35, "BMP2": 35, "SUV39H1": 35, "EGLN3": 35, "CPEB1": 35, "AHSG": 35, "GTF2H5": 35, "PDP2": 35, "MUC1": 35, "TERT": 35, "MCM3": 35, "STAB2": 35, "EPS15": 35, "ANP32A": 35, "E2F6": 35, "RGMB": 35, "CCND2": 35, "NFASC": 35, "HADHA": 35, "RNF14": 35, "HNRNPA1": 35, "DNTTIP2": 35, "MGA": 35, "TNS2": 35, "ACVR1B": 35, "WNT3": 35, "DNAJC5": 36, "PCBP4": 36, "COL4A3BP": 36, "FRAT2": 36, "MAPK6": 36, "RYK": 36, "BMP15": 36, "PLAUR": 36, "GLP1R": 36, "DSP": 36, "GLUD1": 36, "TNFRSF9": 36, "MAGI3": 36, "SPHK2": 36, "FCER1G": 36, "GABPA": 36, "SMS": 36, "SLC7A1": 36, "GNA11": 36, "WNT6": 36, "MYRIP": 36, "HAND1": 36, "AHSA1": 36, "CALCR": 36, "INSR": 36, "PRKAA1": 36, "GZMB": 36, "CBS": 36, "TTL": 36, "PPM1J": 36, "ETS2": 36, "GRM1": 36, "PPP2R1A": 36, "IL1RN": 37, "SETD8": 37, "CSNK2A2": 37, "PNPLA8": 37, "SMEK1": 37, "HSPA5": 37, "GDF15": 37, "PDHA2": 37, "POFUT1": 37, "GRIN2B": 37, "TSSK4": 37, "EZR": 37, "SRSF7": 37, "ITGB6": 37, "ANXA4": 37, "MAPK13": 37, "HTR1B": 37, "LIG4": 37, "PLCB3": 37, "ARVCF": 37, "MYL12B": 37, "PLD1": 37, "NAA10": 37, "ALCAM": 37, "HIST1H2BK": 37, "NCOA2": 37, "SH2B1": 37, "SSTR5": 37, "RARG": 37, "POLD3": 37, "AKAP8": 37, "MAP4K4": 37, "MMP8": 37, "FFAR4": 37, "STXBP6": 37, "AGAP2": 37, "B2M": 37, "AGTR1": 37, "PHACTR3": 37, "ILF3": 37, "NINL": 37, "TNFRSF13C": 37, "RAP1GAP": 38, "CD2": 38, "CDK19": 38, "PLP1": 38, "LMNB1": 38, "NDUFV2": 38, "RAD50": 38, "CRLF1": 38, "CDC25C": 38, "PPIA": 38, "STAMBPL1": 38, "NCK1": 38, "NCF4": 38, "OPRK1": 38, "IL1R2": 38, "PTHLH": 38, "BAK1": 38, "LAIR1": 38, "HHIP": 38, "PLXNB3": 38, "STK11IP": 38, "IL12RB1": 38, "CD38": 38, "DLK1": 38, "MRVI1": 38, "NRGN": 38, "PROC": 38, "CORT": 38, "KIF7": 38, "PMS2": 38, "BMX": 39, "SLC12A1": 39, "SNIP1": 39, "CBX5": 39, "S100A4": 39, "FLOT1": 39, "SLC9A1": 39, "NUP214": 39, "CCR5": 39, "CGB5": 39, "RING1": 39, "TNS3": 39, "C3AR1": 39, "BTRC": 39, "NOG": 39, "DMAP1": 39, "TXK": 39, "PPP1R12B": 39, "TLR3": 39, "PPP1R14D": 39, "CP": 39, "RAPGEF4": 39, "DKK1": 39, "IRAK2": 39, "TRIM8": 39, "PRKRA": 39, "GLRA1": 39, "MEF2C": 39, "CDKN1A": 39, "ACACA": 39, "Q59EE7": 39, "HES1": 39, "PF4": 39, "BAX": 40, "NFIB": 40, "FLT4": 40, "WRAP53": 40, "IL18R1": 40, "PRPF3": 40, "NUP153": 40, "SMYD2": 40, "FPR1": 40, "PLCE1": 40, "ATG7": 40, "ZPR1": 40, "TLR10": 40, "ACKR2": 41, "NR1H2": 41, "PDGFRA": 41, "UBE2E3": 41, "TK1": 41, "GABARAPL1": 41, "GXYLT2": 41, "EIF4ENIF1": 41, "ORC2": 41, "ARFGAP1": 41, "RPS6KA4": 41, "CCL22": 41, "LTBR": 41, "KARS": 41, "PSAP": 41, "CACNA1C": 41, "KRT10": 41, "TNNI1": 41, "PTPN4": 41, "ATG101": 41, "HMOX1": 41, "CDKN2D": 41, "KSR2": 41, "DAK": 41, "RASSF5": 41, "KPNA2": 41, "MCM6": 41, "PARP1": 41, "IL9": 41, "TNFRSF17": 41, "OTUD5": 41, "TRIM29": 41, "SIAH2": 41, "PYCARD": 41, "ORAI1": 41, "PGC": 41, "TNFSF13B": 41, "PNKP": 41, "NREP": 41, "TRIB3": 41, "ABCC8": 41, "CHMP4A": 41, "PHOX2A": 41, "PRM2": 41, "SDC3": 41, "SI": 42, "SMAD1": 42, "DBI": 42, "LPL": 42, "RPGRIP1L": 42, "PLEKHG2": 42, "GRM7": 42, "LGI3": 42, "HOMER1": 42, "GTF2I": 42, "SNX9": 42, "PIAS3": 42, "VRK1": 42, "CABYR": 42, "ATG4B": 42, "GTF2A2": 42, "CSF3": 42, "RBBP7": 42, "SUV39H2": 42, "SMAD3": 42, "PTPRT": 42, "GALP": 42, "GNG4": 42, "TERF2": 42, "AP1M1": 42, "MST1": 42, "BMP1": 42, "DUSP22": 42, "KHSRP": 42, "F10": 42, "SSH2": 42, "GJC1": 42, "SREBF1": 42, "GAS6": 42, "DUSP7": 42, "TCF4": 42, "GOLGA3": 42, "LIN7B": 42, "PITPNM1": 42, "NUCKS1": 42, "SERPINA3": 42, "KCNA2": 42, "IL5RA": 42, "ARPC3": 42, "GFAP": 42, "WNT9B": 43, "GNAZ": 43, "CHP2": 43, "HFE2": 43, "WNT1": 43, "Q59F91": 43, "WDR62": 43, "SCG2": 43, "VRK3": 43, "MYC": 43, "GFRA1": 43, "A0A024R1D6": 43, "DUSP14": 43, "PIDD1": 43, "TEAD2": 44, "PRKCB": 44, "ARFGEF2": 44, "RHOC": 44, "KAT6A": 44, "BCL2L12": 44, "FOSL2": 44, "FBXO32": 44, "ARHGEF18": 44, "AQP2": 44, "PAIP1": 44, "SIRT3": 44, "FRZB": 44, "RETNLB": 44, "PITX3": 44, "PFN1": 44, "GPRC5A": 44, "AATK": 44, "FGF7": 44, "AXL": 44, "TSHB": 44, "NFIX": 44, "TNIP2": 44, "SLC6A2": 44, "ERF": 44, "ATG12": 44, "EIF4G1": 45, "CSF3R": 45, "RANGAP1": 45, "PTPRB": 45, "TDGF1": 45, "IRF4": 45, "HMGA1": 45, "ZMIZ1": 45, "FST": 45, "GEM": 45, "TYROBP": 45, "KDM2A": 45, "GCLM": 45, "STRADB": 45, "NBR1": 45, "SPOP": 45, "CSF2RA": 45, "PTH": 45, "XIAP": 45, "RPL8": 45, "PPM1H": 45, "CREB1": 45, "CLASP2": 45, "CBLC": 45, "CASP2": 45, "EXTL1": 45, "SCP2": 45, "SNAP23": 45, "CXCR3": 45, "MAF": 45, "POLDIP3": 45, "CDCA8": 45, "CCR2": 45, "HUWE1": 46, "PGF": 46, "Q59GJ0": 46, "ITSN1": 46, "CNOT8": 46, "AFP": 46, "LGMN": 46, "AJUBA": 46, "ZFP36L1": 46, "TSC22D3": 46, "NDUFA13": 46, "STK4": 46, "CHP1": 46, "JAK2": 46, "RBM14": 46, "ZEB2": 46, "PTPN2": 46, "SUPT20H": 46, "DYNLRB1": 46, "LRP2": 46, "GAPDH": 46, "RUNX2": 46, "MSI1": 46, "PRSS1": 46, "SHARPIN": 46, "APBA3": 46, "PRMT5": 46, "FGF2": 46, "RASGRF1": 46, "CEBPD": 46, "RNF2": 46, "PITX1": 46, "ENAH": 46, "MAP2K6": 46, "SIRPA": 46, "TAF2": 46, "ACE": 46, "PPARG": 46, "RIMS1": 46, "LIMK2": 46, "YTHDC1": 46, "FLT3LG": 46, "Q9H6U9": 47, "ERCC2": 47, "NR5A1": 47, "TPH2": 47, "CD164": 47, "WNT4": 47, "LHX3": 47, "IGF2BP1": 47, "ITGA7": 47, "RAVER1": 47, "RARRES2": 47, "DYNLL2": 47, "TAGLN2": 47, "CITED1": 47, "GCLC": 47, "BIRC2": 47, "CD74": 47, "PRKACG": 47, "NKIRAS2": 47, "OMG": 47, "SIGLEC6": 47, "QDPR": 47, "TNFRSF1A": 47, "FHOD3": 47, "SP3": 47, "IL12RB2": 47, "CD3G": 47, "FCGR3A": 47, "ERCC6": 47, "FCGR2C": 47, "CDKN3": 47, "CENPU": 48, "IL7R": 48, "GBF1": 48, "SGK1": 48, "STAT5A": 48, "SH3PXD2B": 48, "SPTBN2": 48, "SLC26A5": 48, "TIFA": 48, "IFI16": 48, "IFNAR2": 48, "KLK4": 48, "PTPRD": 48, "NAIP": 48, "RANBP9": 48, "TLR2": 48, "ABCF1": 48, "ARHGEF7": 48, "SHANK2": 48, "KIR2DL3": 48, "PAX7": 48, "MTF1": 48, "LTBP1": 48, "S1PR3": 48, "GLRX": 48, "TRPC4AP": 48, "KITLG": 48, "PNRC1": 48, "GJA5": 48, "CAB39": 48, "A8K270": 48, "DOK2": 48, "HBP1": 48, "SH3BGRL": 48, "PRR5": 48, "DYNC1H1": 48, "PDHA1": 48, "IL20RA": 48, "KIF22": 48, "NFE2L1": 48, "CTDSPL2": 48, "HNRNPL": 48, "DACT2": 48, "PAK6": 48, "STK17B": 49, "MUSK": 49, "SUMO2": 49, "AMOTL2": 49, "MAPRE2": 49, "CCDC88C": 49, "CACNA1A": 49, "PTEN": 49, "HSPE1": 49, "TRPC4": 49, "SARM1": 49, "NCKIPSD": 49, "CCDC6": 49, "Q53EL4": 49, "EXOC4": 49, "DDIT3": 49, "PSME3": 49, "FOXO4": 49, "TREX1": 49, "F3": 49, "Q66SS1": 49, "PPARD": 49, "RUVBL1": 50, "TIMP2": 50, "ARNT": 50, "ITGA10": 50, "SETBP1": 50, "ITGB7": 50, "ATAD2": 50, "AKAP13": 50, "BABAM1": 50, "CCR8": 50, "INHA": 50, "DAPK2": 50, "MAPT": 50, "WISP2": 50, "AZI2": 50, "PTTG1": 50, "PTGES3": 51, "DUSP11": 51, "DVL1P1": 51, "S100A13": 51, "SORBS3": 51, "MAFK": 51, "ITK": 51, "DCN": 51, "TUFM": 51, "CASKIN1": 51, "GCSAM": 51, "CNTNAP2": 51, "SH3GLB1": 51, "GCK": 51, "Q86SX1": 51, "AMHR2": 51, "TBK1": 51, "NR0B1": 51, "RPA1": 51, "ILK": 51, "PARD6G": 51, "ADD3": 51, "GPX1": 51, "CDKN2A": 51, "APTX": 51, "LRRK1": 51, "JAM3": 51, "USP4": 51, "RANBP3": 51, "SSBP3": 51, "PALLD": 51, "NFKBIA": 51, "HOXC8": 51, "RWDD3": 51, "MASP1": 51, "LIG3": 51, "MERTK": 52, "RRM1": 52, "NES": 52, "SOX4": 52, "PDE11A": 52, "NRP1": 52, "NFIC": 52, "TERF2IP": 52, "CLDN4": 52, "CARD14": 52, "GCNT1": 52, "SYTL1": 52, "TAF13": 52, "FOSB": 52, "KIF20A": 52, "CAPRIN2": 52, "A8K0H7": 52, "FCGR2B": 52, "TOB1": 52, "Q59GL5": 53, "STIL": 53, "NABP2": 53, "D9IAI1": 53, "CTNNBIP1": 53, "TTC3": 53, "EPHA2": 53, "NEK2": 53, "PLEK": 53, "PRM1": 53, "SLC12A6": 53, "ACO1": 53, "HLA-A": 53, "Q53H33": 53, "STX3": 53, "KCNB1": 53, "ACAP1": 53, "NLRP10": 53, "CRH": 53, "TCAP": 53, "RNF5": 53, "WHSC1": 53, "PDE5A": 54, "MLH1": 54, "PTK7": 54, "TNFAIP1": 54, "IGFBP3": 54, "ANO9": 54, "PHLDA1": 54, "PRKCSH": 54, "TJP1": 54, "BCL2A1": 54, "KCND2": 54, "PPM1F": 54, "ARFGEF1": 54, "FZD7": 54, "GABRB1": 54, "AXIN2": 54, "PTPN23": 54, "NR3C1": 54, "BCL6": 54, "MASP2": 54, "MKNK1": 54, "CARM1": 54, "TRPV6": 54, "ATF7": 54, "HYAL2": 54, "MSX2": 54, "TAF1": 54, "NANOS1": 54, "SNF8": 54, "SCML2": 54, "SMAD6": 54, "APLP2": 54, "SIX1": 54, "TAF10": 54, "KSR1": 54, "TRPA1": 54, "PSMD2": 54, "FGF19": 54, "PTPRF": 54, "CCRL2": 54, "PAK3": 54, "ELF3": 54, "CHRNB1": 54, "RELN": 54, "MAST2": 55, "HCK": 55, "PRMT1": 55, "EPS8": 55, "OTX1": 55, "PFKFB2": 55, "NPAS2": 55, "DDR1": 55, "KCNA3": 55, "XRCC1": 55, "TBXAS1": 55, "WDFY3": 55, "CDK5": 55, "LMTK2": 55, "CD14": 55, "CALCA": 55, "IL2RB": 55, "C2CD5": 55, "TRIM28": 55, "PDCD6IP": 55, "CYTH1": 55, "GNRH2": 55, "EHD1": 55, "EDA": 55, "CRIPAK": 55, "ERBB4": 56, "CD22": 56, "DBF4": 56, "AKT1S1": 56, "CACNA1I": 56, "USP37": 56, "GPR37": 56, "SEMA3C": 56, "EIF4E": 56, "CD5": 56, "TSPY1": 56, "PATZ1": 56, "GLIS2": 56, "TFCP2": 56, "DLC1": 56, "FOXI1": 56, "ANO7": 56, "ERCC4": 56, "PIK3CD": 56, "GOLPH3": 56, "KAT2B": 56, "CACNA1B": 56, "CDKN2AIP": 56, "KCNA4": 56, "ASF1A": 56, "GNGT1": 56, "ITPRIPL1": 56, "ARHGAP29": 56, "CDCA4": 56, "SNRNP70": 57, "PUF60": 57, "TSNAX": 57, "USP22": 57, "NPPA": 57, "ISG15": 57, "RORC": 57, "LNX1": 57, "YBX1": 57, "CUEDC2": 57, "RALGDS": 57, "PTS": 57, "GNAO1": 57, "PROS1": 57, "DDB1": 57, "RAG1": 57, "ESRRG": 57, "C5AR2": 57, "RECQL": 57, "CIT": 57, "EEA1": 57, "MMP13": 57, "UBQLN1": 57, "JAK3": 57, "RBM38": 57, "CXCL13": 57, "TRIM25": 57, "UBXN1": 57, "NDEL1": 57, "CCL1": 57, "AKAP5": 57, "CLOCK": 57, "LIN7A": 57, "MC5R": 57, "SATB2": 57, "GUCA2B": 57, "PPARA": 57, "NRG4": 57, "SNTA1": 57, "BMP10": 57, "HSBP1": 57, "TRADD": 57, "Q96CY7": 58, "MRGPRX2": 58, "RBL1": 58, "SLC6A4": 58, "VIL1": 58, "CCNG1": 58, "MYD88": 58, "USF2": 58, "AP3B1": 58, "PPP3CC": 58, "NLRC4": 58, "GLI2": 58, "B2RAU8": 58, "GNRH1": 58, "B4DLA6": 58, "CCNL2": 58, "IL1R1": 58, "ALDOA": 58, "AKT1": 58, "IRAK1": 58, "WAPAL": 58, "DDR2": 58, "USP7": 58, "CUL1": 58, "NOV": 58, "PFKFB3": 58, "RAN": 58, "RAB4A": 58, "KLRD1": 58, "ENG": 58, "HSPA4": 58, "HIST2H2BD": 58, "EYA1": 58, "PDIA3": 58, "ARF4": 58, "MXI1": 58, "NCOA1": 58, "PDE4DIP": 58, "PMCH": 58, "ATP5C1": 58, "Q59GM6": 58, "FBXO43": 59, "CASP4": 59, "RACGAP1": 59, "ARHGAP1": 59, "RTN4": 59, "V9HWD6": 59, "VCAM1": 59, "RABGGTB": 59, "MCOLN1": 59, "A0A024R8X1": 59, "ERRFI1": 59, "PTH2": 59, "RASSF6": 59, "PTP4A2": 59, "NR1H3": 59, "TAB3": 59, "TBP": 59, "GCGR": 59, "SORBS2": 60, "PICALM": 60, "NCAM1": 60, "ID3": 60, "ZNF148": 60, "IL4": 60, "SLC4A3": 60, "XBP1": 60, "CRMP1": 60, "SLITRK1": 60, "ESR2": 60, "ESRRA": 60, "PDE4C": 60, "SP7": 60, "RXRB": 60, "GSK3B": 60, "HHAT": 60, "HSF1": 60, "RAD1": 60, "PIK3C2B": 60, "RRM2B": 60, "TRIP12": 60, "HERC5": 60, "UIMC1": 60, "RHOD": 60, "POLA1": 60, "TAOK3": 60, "EXOSC9": 60, "VAV2": 60, "IBSP": 60, "PBX1": 60, "ACKR3": 60, "SORT1": 60, "PTPRC": 61, "MMP2": 61, "FGA": 61, "NRF1": 61, "MYL2": 61, "FNTA": 61, "IFNB1": 61, "CALD1": 61, "MORF4L1": 61, "SLC26A3": 61, "PMS1": 61, "PIK3CG": 61, "CASQ2": 61, "GALR1": 61, "Q15607": 61, "IL31": 61, "BZRAP1": 61, "CARHSP1": 61, "SCN2A": 61, "PARP10": 61, "PIM2": 61, "MAST1": 61, "CUL3": 61, "EPHA1": 61, "HMGB1": 61, "DCTN6": 61, "CXCR1": 61, "CXCL8": 61, "FLNA": 61, "KLF11": 61, "EGR4": 61, "TRIOBP": 61, "ABL2": 61, "Q6AHX3": 61, "MYL1": 61, "GMFB": 61, "NR2F1": 61, "RORB": 61, "KDM3B": 61, "CEBPZ": 61, "UBE2D2": 61, "ACTR2": 61, "MFN2": 61, "TNKS": 61, "MCOLN3": 61, "HIST1H2BO": 61, "TESK1": 61, "AGT": 61, "SIRT1": 61, "ARNT2": 62, "ZNRF3": 62, "GABRG2": 62, "AP2A1": 62, "PAX5": 62, "KCND1": 62, "MAPKAPK5": 62, "PRKAR2B": 62, "ANAPC2": 62, "GRB2": 62, "Q53FE8": 62, "HOMER2": 62, "HLA-C": 62, "RUNX3": 62, "SKP2": 62, "RHO": 62, "KAT8": 62, "ACPP": 62, "ARRB1": 62, "BAIAP2": 62, "GNAT1": 62, "MYBPC3": 62, "RDX": 62, "TSPAN6": 62, "MARS": 62, "TBPL1": 62, "NLRP12": 62, "DSG3": 62, "LYL1": 62, "SLK": 62, "ERCC5": 62, "BSPRY": 63, "GSG2": 63, "GNA12": 63, "B4DNC7": 63, "GHR": 63, "OSBP": 63, "PDIA6": 63, "NR2F2": 63, "FAM195B": 63, "EDN1": 63, "MAP9": 63, "RANBP1": 63, "TFPT": 63, "MYCL": 63, "NKX6-1": 63, "USP21": 63, "ADAM9": 63, "DCX": 63, "CLTB": 63, "SNCG": 63, "CARD10": 63, "ENDOG": 63, "PDPK1": 63, "DOK6": 63, "CDC23": 63, "FANCF": 63, "APH1B": 63, "GRID2": 63, "UNC93B1": 63, "SKP1": 63, "THRA": 63, "GTF2E1": 63, "BCLAF1": 63, "GOPC": 63, "ABCC1": 63, "IKZF3": 63, "NR2E3": 64, "PTTG1IP": 64, "DUSP16": 64, "ETV6": 64, "TAB2": 64, "FHIT": 64, "LIN7C": 64, "DMPK": 64, "GPHA2": 64, "C3": 64, "MAD1L1": 64, "BICD1": 64, "PKD2L2": 64, "MAP2K4": 64, "XRCC3": 64, "IRGC": 64, "TET3": 64, "NRIP1": 64, "TLE1": 64, "BARHL1": 64, "TCL1B": 64, "NGF": 64, "SHCBP1": 64, "UBB": 64, "CACNB4": 64, "NME1": 64, "LIMD1": 64, "HTT": 65, "CTPS1": 65, "TRPM2": 65, "MAFG": 65, "MAPK12": 65, "ARRB2": 65, "CCL8": 65, "RNF43": 65, "FANCM": 65, "CD3E": 65, "PTPRK": 65, "DBN1": 65, "PKNOX1": 65, "NLK": 65, "NKIRAS1": 65, "DCP1A": 65, "RHEBL1": 65, "LCP2": 65, "BRD4": 65, "CASP9": 65, "HNRNPUL1": 65, "POLR2A": 65, "CXCR2": 65, "SKIL": 65, "PLA2G4A": 65, "RCSD1": 65, "INPPL1": 65, "SNAI1": 65, "GTF2H1": 65, "NDUFS4": 65, "TEAD4": 65, "CDC25A": 65, "PTCH1": 65, "NDRG1": 65, "KIF5B": 65, "ECM1": 65, "XPC": 65, "STAU1": 65, "NOTCH1": 66, "CASP6": 66, "COIL": 66, "RAD18": 66, "DBF4B": 66, "AQP5": 66, "RTKN": 66, "EFHD2": 66, "DCK": 66, "PDE10A": 66, "ARPC1B": 66, "CAV1": 66, "KDM6B": 66, "NO66": 66, "RBBP5": 66, "CTNND2": 66, "CD2AP": 66, "HCLS1": 66, "ISL2": 66, "LDHA": 66, "CBY1": 66, "CNKSR2": 66, "Q53HG7": 66, "EED": 66, "GTF2H3": 66, "CMC4": 66, "BRCA1": 66, "PRH2": 66, "HEBP1": 66, "KCNMA1": 66, "TUBA8": 66, "GIT1": 66, "GKAP1": 66, "FXR1": 66, "CAMK2G": 66, "SMAD5": 66, "ARFIP1": 66, "IER3": 66, "ALDH1A2": 66, "CHAF1B": 66, "C7": 66, "IL13RA1": 66, "ACVR1": 66, "C4A": 66, "B3KMX5": 66, "PCBP2": 66, "CCND3": 66, "MSX1": 66, "ADCY1": 66, "STAT2": 66, "PAK1": 67, "MAFF": 67, "YY1": 67, "SF1": 67, "PRDX4": 67, "CRTC2": 67, "EID2": 67, "PLCG1": 67, "TFAP2A": 67, "MAP4K1": 67, "MAP1LC3C": 67, "SNTG2": 67, "HLA-G": 67, "RAE1": 67, "ALDH1A1": 67, "PADI4": 67, "RASGRF2": 67, "POLR2L": 67, "BECN1": 67, "TRIB2": 67, "TLR1": 67, "PBK": 67, "EIF2A": 67, "NEO1": 67, "FOXH1": 67, "BCOR": 67, "CASK": 67, "GRM3": 67, "SHC3": 67, "GRK1": 67, "BRF1": 67, "KIF23": 67, "MYH10": 67, "EEF1E1": 67, "BHLHE41": 67, "LAMB1": 67, "SCNN1A": 67, "PRKCE": 67, "STRA13": 67, "GRIK1": 67, "FHL2": 67, "TDP1": 67, "RPL12": 67, "IFITM1": 67, "HTR2A": 67, "FRS3": 67, "CXCL12": 67, "CCP110": 67, "IL18BP": 68, "RPAP2": 68, "IFNW1": 68, "RANBP2": 68, "WDR48": 68, "CNTN1": 68, "ATG16L1": 68, "TSLP": 68, "TCF7": 68, "SHOX": 68, "SNCAIP": 68, "SRY": 68, "LIPC": 68, "GPHN": 68, "DEFB103B": 68, "PYGO1": 68, "SIN3A": 68, "KRT2": 68, "PXN": 68, "FGF22": 68, "OXSR1": 68, "THOP1": 68, "KCNMB4": 68, "TNNT2": 68, "GDF6": 68, "POU4F3": 68, "ANGPTL1": 68, "TEX14": 68, "RND1": 68, "ACTN4": 68, "NR2F6": 68, "BRD2": 68, "SPN": 68, "CLK4": 68, "EIF6": 68, "PPP1R3D": 68, "IL21": 69, "EDN3": 69, "TLR4": 69, "STAG2": 69, "TACC1": 69, "SP4": 69, "CBX3": 69, "MITF": 69, "PIP4K2B": 69, "TP53INP2": 69, "PDE1A": 69, "TNFRSF1B": 69, "HIST1H1B": 69, "CREB3L1": 69, "CDK11B": 69, "CCL24": 69, "SUFU": 69, "SNX4": 69, "FOSL1": 69, "VCL": 69, "DLGAP5": 69, "EPC1": 69, "AICDA": 69, "FZD9": 69, "NFE4": 69, "NUMA1": 69, "UNG": 69, "RHOG": 69, "CLEC7A": 69, "NME2": 69, "DTNB": 70, "SSR2": 70, "IL1RL1": 70, "SPDYA": 70, "PHKG1": 70, "SFTPD": 70, "ITGB4": 70, "HRH4": 70, "KAT6B": 70, "CSNK2B": 70, "DRD1": 70, "DAB2": 70, "KDM4A": 70, "LAMA5": 70, "NEK6": 70, "CFTR": 70, "SNX18": 70, "GADD45GIP1": 70, "GNAI3": 70, "TFAP2C": 70, "N4BP1": 70, "PGM3": 70, "UBE2V2": 70, "VPS37B": 70, "SCN4A": 70, "CTNNA2": 70, "CRYGC": 70, "RFC2": 70, "IL22RA2": 70, "FANCC": 70, "MAP1B": 70, "PTGER3": 70, "CTCF": 70, "TNFSF14": 70, "PLK4": 70, "STK17A": 70, "SCNN1G": 70, "PPP2R2A": 70, "ALPP": 70, "PARVA": 70, "MFNG": 70, "TMF1": 70, "TSC2": 70, "FAF1": 70, "CNP": 70, "NOD2": 70, "LAT2": 70, "HIST1H2BE": 71, "IFNAR1": 71, "THPO": 71, "MYBL2": 71, "SOD3": 71, "SS18L1": 71, "DACH2": 71, "PTTG2": 71, "RET": 71, "ACP1": 71, "CCR10": 71, "V9HW25": 71, "FLNC": 71, "EIF4EBP3": 71, "ATF2": 71, "RASGRP2": 71, "FDXR": 71, "NCS1": 71, "GRPR": 71, "CRB1": 71, "CLK2": 71, "APAF1": 71, "KCNAB2": 71, "ZNF692": 71, "PHF8": 71, "GSTP1": 71, "EIF4E2": 71, "A2M": 71, "SYT6": 71, "TRIM37": 71, "TRIM21": 71, "FANCL": 71, "MOGS": 71, "EDF1": 71, "CTTN": 71, "F8": 71, "CDC16": 71, "OTUB1": 71, "RGS13": 71, "GALC": 71, "STX1A": 71, "KHDRBS2": 72, "SH2D3A": 72, "TIGIT": 72, "TRAF2": 72, "GPR1": 72, "MCM2": 72, "TINF2": 72, "CTDP1": 72, "MAPK11": 72, "CRYBA1": 72, "SERPINA1": 72, "MYL3": 72, "TRAF4": 72, "TP53TG5": 72, "COL1A2": 72, "CCL3L3": 73, "ITGB3BP": 73, "PSMC3IP": 73, "FMR1": 73, "TUBB6": 73, "WNK3": 73, "LSR": 73, "TRPV4": 73, "LAX1": 73, "Q59EH3": 73, "RFWD2": 73, "CRY1": 73, "ABCC3": 73, "ETF1": 73, "PGM1": 73, "UBE2V1": 74, "NLGN4X": 74, "TANK": 74, "RUSC1": 74, "ATRX": 74, "SLC12A3": 74, "FHL1": 74, "USF1": 74, "XPO5": 74, "CDK6": 74, "ICMT": 74, "SULT4A1": 74, "DYRK2": 74, "TPST1": 74, "GMNN": 74, "CA3": 74, "PROM1": 74, "BLK": 74, "ATG16L2": 74, "SGK3": 74, "PVRL1": 74, "NFKB1": 74, "MAP3K4": 74, "ARFIP2": 74, "DUSP8": 74, "KCNIP3": 74, "RPS19BP1": 74, "PDGFC": 74, "FLNB": 74, "PSMA6": 74, "SEC13": 74, "NET1": 74, "CDC6": 74, "PPM1K": 74, "CD33": 74, "RASIP1": 74, "DIAPH1": 74, "WNT8B": 74, "TGFBR1": 75, "SETD1A": 75, "MUL1": 75, "CPLX1": 75, "NAP1L1": 75, "RSC1A1": 75, "CAMK2D": 75, "CTNNA3": 75, "MAGOH": 75, "JAZF1": 75, "CXCL1": 75, "PDGFB": 75, "NUAK1": 75, "TNFSF9": 75, "CASP7": 75, "SDC1": 75, "CHRNA1": 75, "HEY1": 75, "STK25": 75, "LBR": 75, "FLI1": 75, "ARPC5": 75, "SFI1": 75, "GLRX3": 75, "CLCF1": 75, "TUBB2B": 75, "PRKDC": 75, "CA9": 75, "ST8SIA4": 75, "HDAC7": 75, "STX17": 75, "ARHGEF2": 75, "PTGER2": 75, "MAP3K1": 75, "NOD1": 75, "RNF8": 75, "SMARCB1": 75, "FOXL2": 75, "TGS1": 75, "KCNQ1": 75, "VAV1": 75, "MAP1A": 75, "PPP3R1": 75, "UBE2E1": 75, "TCEB2": 75, "TH": 75, "HINFP": 75, "GUCA2A": 75, "GABARAPL2": 75, "A8K9W7": 76, "NEIL1": 76, "FKBP1A": 76, "DTX4": 76, "MATR3": 76, "AQP4": 76, "TYRO3": 76, "MACROD1": 76, "NTRK1": 76, "SENP2": 76, "TAGLN": 77, "JADE1": 77, "SLN": 77, "Q9BRL5": 77, "MSC": 77, "EIF3C": 77, "NDN": 77, "ZNF239": 77, "AQP9": 77, "CSNK2A1": 77, "HSF4": 77, "CTSK": 77, "NIPSNAP1": 77, "CHEK1": 77, "XAF1": 77, "CRX": 77, "SELE": 77, "ROR2": 77, "RABAC1": 77, "SENP1": 77, "ERCC8": 77, "BRAF": 77, "PRKD3": 77, "FGF1": 77, "RPTOR": 77, "PSMB9": 77, "CTDSPL": 77, "PTAFR": 77, "SNAP25": 77, "KCNJ5": 78, "C1D": 78, "RPN1": 78, "SCN3A": 78, "POLM": 78, "MCM7": 78, "EFNA3": 78, "DUPD1": 78, "KLRC2": 78, "NR2C2": 78, "ADRA2A": 78, "INA": 78, "SAA1": 78, "SRSF3": 78, "SMPD3": 78, "CAPZA2": 78, "MTBP": 78, "KRT19": 79, "NELFCD": 79, "CDH15": 79, "CD226": 79, "POLK": 79, "TAF6": 79, "MYBL1": 79, "NR0B2": 79, "ANXA2": 79, "GRP": 79, "CFB": 79, "SESN1": 79, "MNT": 79, "CAPN3": 79, "IFITM3": 79, "SP100": 79, "MAP3K8": 79, "BMPR1A": 79, "S1PR1": 79, "GUSB": 79, "MYOM1": 79, "GTF2F2": 79, "PAK7": 79, "TLR8": 79, "REM1": 79, "TMED7": 79, "HCN4": 79, "EIF2B5": 79, "DLG2": 79, "VCPIP1": 79, "SOCS5": 79, "Q53GA5": 79, "PTGIR": 79, "COX4I2": 79, "PDIK1L": 79, "TAB1": 80, "RASSF2": 80, "IFIT2": 80, "ATPIF1": 80, "WIPI2": 80, "GADD45B": 80, "WDR12": 80, "PPP2R1B": 80, "CORO7": 80, "IQGAP2": 80, "IFNLR1": 80, "GEMIN5": 80, "DUT": 80, "MC3R": 80, "Q59GY7": 80, "SYT1": 80, "CHAMP1": 80, "TCF3": 80, "HIPK3": 80, "KCNJ13": 80, "POU2AF1": 80, "ELANE": 80, "LRRC1": 80, "FGF18": 80, "GATA3": 80, "CCNY": 80, "PCM1": 81, "UCN2": 81, "SMPD1": 81, "DDX5": 81, "PLRG1": 81, "CHRM1": 81, "DFFB": 81, "IFIH1": 81, "SOCS6": 81, "SLC5A3": 81, "F2RL3": 81, "RBM8A": 81, "ARAP1": 81, "KRT8": 81, "THRB": 81, "SHH": 81, "NHEJ1": 81, "PIN4": 81, "NCOR2": 81, "LHB": 81, "CXCL11": 81, "CHN1": 81, "COPS5": 81, "NMT1": 81, "REV1": 81, "CDC34": 81, "HOXC9": 81, "SLX4": 81, "SV2A": 81, "NKX2-1": 81, "TNFRSF4": 81, "HUS1": 81, "DEF6": 81, "PPP1R10": 81, "FAM160B2": 82, "CDH2": 82, "SRPK1": 82, "MLLT1": 82, "ARAF": 82, "FER": 82, "NOX4": 82, "PPP2CB": 82, "SNTB2": 82, "BRAP": 82, "V9HW43": 82, "Q7Z370": 82, "TCEAL1": 83, "MCM10": 83, "ARNTL": 83, "TBL1XR1": 83, "MBD4": 83, "GRIN1": 83, "DCLRE1A": 83, "DAXX": 83, "SLC25A1": 83, "CD36": 83, "NPPB": 83, "PER3": 83, "MAPKAPK3": 83, "TEAD3": 83, "CNTFR": 83, "GH1": 83, "IRS1": 83, "CDR2": 83, "SET": 83, "PAM": 83, "ATP2A1": 83, "UGT1A7": 83, "STMN3": 83, "PENK": 83, "MSN": 83, "AR": 83, "GTF2A1L": 83, "PGAM5": 83, "ANKRD17": 83, "EIF3F": 84, "ZNF76": 84, "EIF4EBP1": 84, "TLN1": 84, "XPA": 84, "NEK1": 84, "SPAG5": 84, "NEK9": 84, "TUT1": 84, "SFRP4": 84, "POP1": 84, "MALT1": 84, "ZKSCAN3": 85, "GAB1": 85, "EIF4G3": 85, "MAP3K12": 85, "LIME1": 85, "CKAP2": 85, "FHL3": 85, "RASGEF1A": 85, "NLRX1": 85, "EXO1": 85, "DCLRE1B": 85, "GDA": 85, "DOCK1": 85, "BLVRA": 85, "RPH3A": 85, "MAFB": 85, "S100B": 85, "NEB": 85, "PDIA4": 85, "PTK2": 85, "MGP": 85, "TBC1D25": 85, "FBXO7": 85, "ACHE": 85, "CD8A": 85, "GDF11": 85, "KLHL3": 85, "DEFB4B": 85, "CCL16": 85, "MAGI1": 85, "EIF3M": 85, "VAV3": 85, "NDUFAF1": 85, "MMP24": 85, "GXYLT1": 85, "PINK1": 85, "CRYBA4": 85, "MAP3K14": 85, "ACVR2A": 85, "RAB3IP": 85, "HTRA2": 85, "TCEA2": 86, "MCM8": 86, "NFYB": 86, "DNM1L": 86, "ITPR2": 86, "PARK7": 86, "THRAP3": 86, "SGK2": 86, "OSMR": 86, "LYZ": 86, "B4DGH1": 86, "CDC20": 86, "FOXO6": 86, "SPTBN1": 86, "CYTH2": 86, "RAC2": 87, "PRKCQ": 87, "CENPA": 87, "HCRTR2": 87, "PELP1": 87, "KPNA4": 87, "IGF1R": 87, "EPHA8": 87, "CEBPG": 87, "SHB": 87, "PLAT": 87, "PPP2CA": 87, "RCHY1": 87, "CIITA": 87, "FBXO11": 87, "IL2RA": 87, "MAPRE1": 87, "SNX2": 87, "BATF": 87, "HNRNPA2B1": 87, "POU4F2": 87, "ITGB1": 87, "SYNCRIP": 87, "ANAPC11": 87, "KPNB1": 87, "NLRP7": 87, "NEUROD1": 87, "EIF2S3": 87, "RPS6KA1": 88, "TECPR1": 88, "SIRT2": 88, "HRH1": 88, "ACKR1": 88, "HCRT": 88, "ERBB2": 88, "TRIM14": 88, "NFYA": 88, "RPS6KA3": 88, "DTX1": 88, "KIF2A": 88, "KCNQ3": 88, "AMH": 88, "TLK1": 88, "Q59GC5": 88, "ELK1": 88, "NCK2": 88, "HTR2C": 88, "TNFSF13": 88, "RNF11": 88, "DISP1": 88, "IFNA2": 88, "MAPK10": 88, "SLC3A2": 88, "DUSP12": 88, "CCL2": 88, "CEP152": 88, "RIPK3": 88, "IL7": 88, "IFNA13": 88, "PELI2": 88, "ZIC1": 88, "RNF24": 88, "HMX3": 88, "UMOD": 88, "MAF1": 88, "CHEK2": 88, "PRKG2": 88, "VDAC2": 88, "B3KMX0": 88, "GTF3C4": 88, "FASLG": 88, "CRY2": 89, "UBR1": 89, "TYR": 89, "RICTOR": 89, "IGSF8": 89, "CYP17A1": 89, "TOPBP1": 89, "ANXA2P2": 89, "MAPK8IP2": 89, "PPM1B": 89, "RGS6": 89, "TSHR": 89, "UNC13B": 89, "VPS72": 89, "IRF8": 89, "SLC47A1": 89, "TRPV5": 89, "RBM12B": 89, "NXF1": 89, "PYGB": 89, "MPP5": 89, "HNRNPD": 89, "PSMD11": 89, "LMNA": 89, "H3F3B": 89, "PRKD2": 89, "LRP8": 89, "IFIT3": 89, "HIST1H3B": 89, "COPS7A": 89, "CD3EAP": 89, "CCNB2": 89, "IKBKG": 89, "ZNHIT1": 89, "KIF3A": 89, "SMARCD3": 89, "MMP16": 89, "GTF2B": 89, "TADA3": 89, "CCM2": 89, "DIXDC1": 89, "ACTC1": 90, "RGS4": 90, "OTX2": 90, "MAPKAPK2": 90, "MC4R": 90, "TFDP1": 90, "SUV420H2": 90, "PARK2": 90, "SFTPA2": 90, "TRPM6": 90, "HOXB8": 90, "SPNS1": 90, "RAC3": 90, "MXD3": 90, "TPD52L1": 90, "PSTPIP1": 91, "CR1": 91, "NOLC1": 91, "MIF": 91, "LSP1": 91, "CFL2": 91, "PLXNB2": 91, "CDC5L": 91, "SMO": 91, "FKBP4": 91, "MUC5AC": 91, "SYP": 91, "TXNRD1": 91, "MAGEA1": 91, "RUVBL2": 91, "DNAJA3": 91, "PTP4A3": 92, "ADAM17": 92, "SIPA1": 92, "ENTPD1": 92, "PLK3": 92, "GLO1": 92, "ACTN2": 92, "HIST1H2BN": 92, "INHBA": 92, "CAPZA1": 92, "EME1": 92, "PROX1": 92, "CFH": 92, "RFX5": 92, "SNPH": 92, "CABLES2": 92, "MLF1": 92, "WIF1": 92, "HNRNPU": 92, "SEC16B": 92, "DNM2": 92, "TTF2": 92, "PPP1R12A": 92, "KDM4C": 92, "PDE4D": 92, "BARD1": 92, "PCLO": 93, "SSU72": 93, "NEIL2": 93, "USP20": 93, "HIST1H1C": 93, "RPS15": 93, "NRCAM": 93, "MYO1C": 93, "GBGT1": 93, "HELLS": 93, "AIP": 93, "EGR1": 93, "WASF2": 93, "IHH": 93, "STRAP": 93, "SFRP2": 93, "WBP2": 93, "HSPA14": 93, "GAST": 93, "CBFB": 93, "V9HWA5": 93, "LTB4R2": 93, "IBTK": 93, "CCL7": 93, "GTPBP2": 93, "NUP98": 93, "CSDC2": 93, "LTA4H": 93, "HIST1H2BL": 93, "IFNA17": 93, "NMB": 93, "CETN1": 93, "UBE2L3": 94, "TESK2": 94, "CDK20": 94, "PAK4": 94, "CNTNAP1": 94, "HSP90B1": 94, "PIP5K1B": 94, "CYP19A1": 94, "CEBPE": 94, "DIAPH3": 94, "NRAS": 94, "MSH2": 94, "GMPS": 94, "TRIM27": 94, "PPP2R5A": 94, "A8K171": 94, "CNBP": 94, "ESR1": 94, "THBD": 94, "G3BP1": 94, "PPP1R14A": 94, "TFPI": 94, "ATF4": 94, "CDC7": 94, "EPX": 94, "PIK3AP1": 94, "COL4A3": 94, "CCNC": 94, "TRAF3IP1": 95, "DDX20": 95, "POLR2F": 95, "MIR17HG": 95, "MEN1": 95, "SUZ12": 95, "VTN": 95, "USP25": 95, "TET2": 95, "Q9UME6": 95, "DLX3": 95, "GNB2L1": 95, "CFL1": 95, "B3KWN9": 95, "ITGB2": 95, "PIM1": 95, "WASF1": 95, "ROR1": 95, "CCAR2": 95, "SUB1": 95, "GNA15": 95, "PNOC": 95, "RABEP1": 95, "CYP2B6": 95, "CDH1": 95, "WNT5B": 95, "HNRNPM": 95, "TNFSF8": 95, "H2BFS": 95, "SPDEF": 95, "DTX3L": 96, "ITGB3": 96, "KLRC3": 96, "PTPRS": 96, "EPHB3": 96, "INADL": 96, "KL": 96, "KRAS": 96, "GAP43": 96, "CDCA5": 96, "ROCK2": 96, "G6PC": 96, "MYH9": 96, "ETS1": 96, "HDAC3": 96, "SYN2": 96, "SERPINF1": 96, "FXYD1": 96, "PLSCR4": 96, "ERBB2IP": 96, "HLA-E": 96, "MARCKS": 96, "BCL2": 96, "MEF2B": 96, "CRYBB2": 97, "STRADA": 97, "REC8": 97, "IRF5": 97, "DLX5": 97, "DUSP5": 97, "KLF8": 97, "MPLKIP": 97, "ALPI": 97, "GAD1": 97, "HMGN1": 97, "PACSIN1": 97, "F2RL1": 97, "GALR2": 97, "LRRFIP2": 97, "S100A8": 97, "CDYL": 97, "MCL1": 97, "IL6R": 97, "ROCK1": 97, "TPR": 97, "MAP2": 97, "PSMB10": 97, "TDG": 97, "RANBP17": 97, "EP400": 97, "ZAP70": 97, "MPL": 97, "RBCK1": 97, "CALM2": 97, "ADAM12": 97, "GSK3A": 97, "GFRA2": 97, "CSK": 97, "PCSK2": 98, "PLCG2": 98, "MAL": 98, "CAST": 98, "SREBF2": 98, "SLC11A1": 98, "SIK1": 98, "MTCP1": 98, "AP2M1": 98, "NMNAT1": 98, "GATA4": 98, "DUSP26": 98, "PLK2": 98, "RASA4": 98, "TARDBP": 98, "SLC18A2": 98, "CASP3": 98, "MEFV": 99, "LPXN": 99, "LPIN1": 99, "MDFI": 99, "IL3RA": 99, "LYAR": 99, "PPFIA1": 99, "TNFRSF14": 99, "CHD8": 99, "ITGA9": 99, "CCL21": 99, "PRKAR1A": 99, "TNFRSF10B": 99, "TAOK2": 99, "NSUN2": 99, "DHFR": 99, "CLCA2": 99, "SMURF2": 99, "FGF4": 99, "CDK10": 99, "CXCL2": 99, "CD80": 99, "BANK1": 99, "B3KXJ4": 99, "KDM5D": 99, "CUL5": 99, "LGR6": 99, "CEP164": 99, "CDC42SE1": 99, "RABGEF1": 99, "EIF3B": 99, "GP1BB": 99, "IFNL2": 99, "GNG12": 99, "GRK4": 99, "IL13RA2": 99, "FRK": 99, "CTH": 99, "ZFP36": 99, "TTBK1": 99, "PCBP1": 99, "ATP6AP2": 99, "FYN": 99, "IL1B": 99, "MDK": 99, "ITGAV": 100, "FAM20C": 100, "GNAQ": 100, "ASPH": 100, "NKX3-1": 100, "FSHR": 100, "FURIN": 100, "DSG1": 100, "SMARCA1": 100, "DUSP2": 100, "ITCH": 100, "EDC3": 100, "TGFB1I1": 100, "RBM17": 100, "FGF23": 100, "SLC9A3": 101, "NFATC4": 101, "PSIP1": 101, "DNMT3L": 101, "TGM1": 101, "PTRH2": 101, "PDE4B": 101, "WNT3A": 101, "PPHLN1": 101, "COX5B": 101, "TRAF1": 101, "WIZ": 101, "PAF1": 101, "SH3KBP1": 101, "GIT2": 101, "KISS1R": 101, "ADAMTS5": 101, "AMFR": 101, "IKZF1": 101, "PARD6A": 101, "MYOD1": 101, "CXCR5": 101, "TRPV3": 101, "NOS2": 101, "WWTR1": 101, "LAMA3": 101, "MAP7": 101, "BIRC5": 101, "CISH": 101, "RNF168": 101, "UQCRC2": 101, "SERPINE1": 101, "GNAS": 101, "ERLIN1": 101, "ATRIP": 101, "IL12B": 101, "PPA1": 101, "CDX1": 101, "PPP1R9A": 101, "RIPK1": 101, "HDAC8": 101, "POT1": 101, "CNN3": 101, "GRB10": 101, "AK1": 101, "NDRG2": 101, "AURKC": 101, "TREM1": 102, "ECT2": 102, "MAPRE3": 102, "CLIC5": 102, "ITGA2": 102, "JARID2": 102, "ATOH1": 102, "RELB": 102, "SPRED2": 102, "NEK7": 102, "CLCA1": 102, "EIF5": 102, "NOXO1": 102, "NCAPH": 102, "DLL1": 102, "NFATC2": 102, "CHN2": 102, "TGFBR3": 102, "CCL26": 102, "CAPN2": 102, "PTCRA": 102, "NAB1": 102, "TRPM8": 102, "COL18A1": 102, "BRSK1": 102, "AMBRA1": 102, "SIVA1": 102, "ZBTB16": 102, "BRCC3": 102, "RGMA": 102, "ADIPOQ": 102, "FABP4": 102, "MTMR2": 102, "GTF3A": 102, "VCAN": 103, "SEPT5": 103, "PTPN14": 103, "CCDC65": 103, "FNBP1": 103, "SSBP1": 103, "TNIP1": 103, "CCNT2": 103, "GHSR": 103, "ECE1": 103, "PSME2": 103, "IL32": 103, "NGFR": 103, "CTLA4": 103, "DDX17": 103, "SEMA4D": 103, "FOXC1": 103, "TIMELESS": 103, "SLC9A3R2": 103, "RFWD3": 103, "SCAF11": 103, "CDO1": 103, "MARCH7": 103, "PSMA7": 103, "VWF": 103, "CELF1": 103, "PPP2R3B": 103, "IL13": 103, "WIPF1": 103, "CA2": 103, "HNRNPA0": 103, "GDF2": 103, "CNTF": 103, "CD47": 103, "DGUOK": 103, "EPHA5": 103, "IL6ST": 103, "GYS1": 103, "JAM2": 103, "XPO1": 103, "TRAF3": 103, "PDE6D": 103, "PSMA4": 104, "HIST1H2BJ": 104, "ID4": 104, "RPA2": 104, "ETV4": 104, "FAAP20": 104, "PGR": 104, "MYF6": 104, "CBX4": 104, "PTH2R": 104, "MYO6": 104, "TNFRSF18": 104, "BATF3": 104, "Q53ES7": 104, "CD3D": 104, "BAMBI": 104, "STK39": 104, "MTA2": 104, "SUGT1": 104, "POLD4": 104, "PJA2": 104, "EPM2A": 104, "ADCY7": 104, "IDH2": 104, "SEPT4": 104, "TLR5": 104, "PI4KB": 104, "GPI": 104, "SIN3B": 104, "LFNG": 104, "DAG1": 104, "DYNC1I2": 104, "BORA": 104, "CARD18": 104, "STAP2": 104, "BANP": 104, "PRKRIR": 104, "HK1": 104, "PHKA1": 104, "GRIN2A": 104, "IL19": 104, "MEIS2": 105, "JUNB": 105, "NSFL1C": 105, "NLRC5": 105, "TAL1": 105, "TAX1BP1": 105, "DLK2": 105, "CHD3": 105, "PPIB": 105, "HRAS": 105, "GRAP": 105, "TUBA1C": 105, "MRAS": 105, "EBAG9": 105, "NCL": 105, "A8K5M4": 106, "NIN": 106, "MAP4K2": 106, "FANCA": 106, "DEDD": 106, "ZFHX3": 106, "BDKRB2": 106, "KREMEN1": 106, "TNC": 106, "EXOC5": 106, "WASF3": 106, "SMARCA4": 106, "CD97": 106, "TRIP10": 106, "KLF3": 106, "ELK4": 106, "PLCB2": 106, "AKAP11": 106, "CTSF": 106, "SNTG1": 106, "REPS2": 106, "DTL": 106, "Q59E85": 106, "SENP3": 106, "RYBP": 106, "ZNF350": 106, "WEE1": 106, "RYR2": 106, "PLA2G1B": 106, "RAB11A": 106, "TLX1": 106, "RALB": 106, "OCLN": 106, "FGG": 106, "GTF2H2": 106, "STAT3": 107, "BAG4": 107, "TRIM63": 107, "UCN": 107, "GRIA2": 107, "B2R8B5": 107, "RAD21": 107, "B4DU40": 107, "TCL1A": 107, "SFRP1": 107, "NEDD8": 107, "KIF2C": 107, "IL20": 107, "NCOR1": 107, "GABRA1": 107, "MSH5": 107, "CD300LF": 107, "WNT7B": 107, "DOCK7": 107, "CNTNAP4": 107, "RNF4": 107, "MED28": 107, "CETN3": 107, "NKRF": 107, "GTF2E2": 107, "ZBTB17": 107, "CLK1": 107, "MAPK4": 107, "KLF10": 107, "CPE": 107, "GSPT2": 107, "IRF2": 107, "BCR": 107, "USP14": 107, "FOXI2": 107, "DUSP4": 107, "HOXA1": 107, "BCL2L11": 107, "KAT7": 108, "SYNJ2": 108, "MMP15": 108, "SPTLC1": 108, "IL31RA": 108, "MME": 108, "SOX9": 108, "CHRM2": 108, "ITGA6": 108, "THBS2": 108, "XRCC5": 108, "DUSP23": 108, "TTF1": 108, "SMG6": 108, "MAFA": 108, "TSPYL2": 108, "SIGLEC10": 108, "TXN": 108, "SYT4": 108, "GOLGA2": 108, "LITAF": 108, "IGF2R": 108, "KMT2E": 109, "ZC3H18": 109, "PREX2": 109, "MAPK15": 109, "FZD10": 109, "PRDX3": 109, "BMI1": 109, "BLNK": 109, "PTPRZ1": 109, "KDM5B": 109, "IRAK3": 109, "PTPN6": 109, "CLCN3": 109, "EIF3D": 109, "THY1": 109, "IRS4": 109, "E2F4": 109, "KCNK9": 110, "ETV5": 110, "FANCG": 110, "MYLK": 110, "SCAP": 110, "DEFB104B": 110, "TIPIN": 110, "KRT85": 110, "CCR4": 110, "SMARCAL1": 110, "E4F1": 110, "CRLF2": 110, "WRN": 110, "BRIP1": 110, "PSEN2": 110, "FBXO5": 110, "TGFB1": 110, "ARHGEF4": 110, "GSTA1": 110, "SMARCE1": 110, "CAPN1": 110, "MSH6": 110, "KDM6A": 110, "PHF6": 110, "IL11RA": 110, "Q86T74": 110, "SSB": 110, "DYRK3": 110, "CSNK1A1": 110, "CEP55": 110, "BMP7": 110, "SLTM": 110, "SOS2": 110, "EEF2": 110, "SUMO1": 110, "DLAT": 111, "GJB1": 111, "APIP": 111, "RAB23": 111, "EEF2K": 111, "E2F2": 111, "IL5": 111, "RHOU": 111, "ELP3": 111, "ELF4": 111, "MAPK7": 111, "EP300": 111, "CLTA": 111, "GPC4": 111, "SRSF2": 111, "Q96FS5": 111, "HIST2H2BC": 111, "SEPT2": 111, "DYNLL1": 111, "FZD6": 111, "NMRAL1": 111, "TAF11": 111, "POLI": 112, "CLDN1": 112, "HAS2": 112, "NKX2-5": 112, "GNB3": 112, "MMP14": 112, "CD79A": 112, "BBC3": 112, "DAPK3": 112, "MBD1": 112, "BAG2": 112, "RPS6": 112, "STAM2": 112, "RAB2A": 112, "TGIF1": 112, "MAP3K5": 112, "SOD2": 112, "APC": 112, "AAK1": 112, "SEPT3": 112, "SIGLEC5": 112, "UBA7": 112, "NDUFB10": 112, "SERPINB3": 112, "MAST3": 112, "LTA": 112, "UBE2M": 112, "AKAP12": 112, "DEPTOR": 112, "CSNK1G2": 112, "ZAK": 112, "IL1A": 112, "PDP1": 112, "RCC1": 112, "EIF2S2": 112, "Q9BSD8": 112, "MCHR2": 112, "REPS1": 112, "B4GALT1": 113, "HMGA2": 113, "CORO1C": 113, "C5": 113, "PAK1IP1": 113, "PADI1": 113, "TXNIP": 113, "SRGAP3": 113, "SHC1": 113, "KCNA1": 113, "NOTCH2": 113, "HSP90AB1": 113, "KCNN2": 113, "KIR2DL4": 113, "REV3L": 113, "NPHP1": 113, "CST4": 113, "MGEA5": 113, "APOBEC3G": 113, "EPHA6": 113, "KLC2": 113, "ADRM1": 113, "CASP1": 113, "RNF111": 113, "CPM": 113, "CD163": 113, "EIF2AK1": 113, "SPAG9": 113, "CTSS": 113, "RPS6KB2": 113, "KDM1A": 113, "TRAT1": 113, "FOXM1": 113, "RNF7": 113, "GDI1": 113, "UNC119": 113, "CDC73": 113, "RRAS2": 113, "MMP12": 114, "ANGPT4": 114, "JUP": 114, "SND1": 114, "SOCS2": 114, "ENC1": 114, "DPYSL2": 114, "TAPBP": 114, "HDAC5": 114, "STXBP1": 114, "CD151": 114, "TGM2": 114, "VEGFC": 114, "CHRM4": 114, "LTF": 114, "PDE1B": 114, "GSN": 114, "RPAP3": 114, "MBTPS1": 114, "CAMKK1": 114, "NGEF": 114, "KCTD10": 114, "DCTN1": 114, "ERCC6L": 114, "DEDD2": 115, "B2R7U3": 115, "CUX1": 115, "YWHAQ": 115, "SNW1": 115, "TOLLIP": 115, "TCEB3": 115, "MMP1": 115, "FNTB": 115, "PALB2": 115, "SQSTM1": 115, "P08107": 115, "PCSK5": 115, "CDC42EP4": 115, "SDC4": 115, "PRKCA": 115, "BTC": 115, "CANX": 115, "LAMA1": 115, "SATB1": 115, "IAPP": 115, "PSMC3": 115, "CDK5RAP3": 115, "PKP4": 115, "CCNO": 115, "RFNG": 115, "PDK4": 115, "STK10": 115, "SMC1A": 115, "TSC1": 115, "NEK11": 115, "MDM4": 115, "PAWR": 115, "USP10": 115, "IFT57": 116, "DES": 116, "DAPK1": 116, "TAOK1": 116, "PYGO2": 116, "PRKAG3": 116, "ILF2": 116, "DPYSL3": 116, "TCF7L2": 116, "HABP4": 116, "ASH1L": 116, "SRC": 116, "MYL12A": 116, "CCNT1": 116, "PLSCR1": 116, "AQP1": 116, "RRN3": 116, "ASGR2": 116, "PTPRO": 116, "ADD2": 116, "BDNF": 116, "IGF1": 116, "NEFM": 116, "BIRC3": 116, "SYT11": 116, "BOC": 116, "ASB2": 116, "EGFR": 117, "MS4A2": 117, "TFEB": 117, "SLIT1": 117, "RASA1": 117, "MARK2": 117, "KIR3DL1": 117, "RPS21": 117, "UGT2B7": 117, "CCL23": 117, "BAD": 117, "GRN": 117, "IL37": 117, "ICAM3": 117, "HAX1": 117, "RGS2": 117, "HIST1H2BB": 117, "CDCP1": 117, "ARPC2": 117, "RECQL4": 117, "SNX33": 117, "SDCBP": 117, "APBB1": 117, "MINK1": 117, "WDR5": 118, "XRCC6": 118, "NPHS1": 118, "Q9P0T0": 118, "USP6NL": 118, "GEMIN4": 118, "TRPC3": 118, "SCN1A": 118, "RMDN3": 118, "RAP1A": 118, "STMN1": 118, "APPL1": 118, "HSPD1": 118, "NDC80": 118, "FGR": 118, "ATXN2L": 118, "PDX1": 118, "ADD1": 118, "XRCC4": 118, "KMT2A": 118, "PLEC": 118, "NTF3": 118, "CRKL": 118, "GPSM1": 118, "MAP2K5": 118, "FOXA1": 118, "NEDD9": 118, "RBM4": 118, "DRD2": 118, "HNF4A": 118, "EPO": 118, "SETD2": 118, "PTPN21": 118, "RB1": 118, "GUCY1B3": 119, "ADRB2": 119, "MT3": 119, "MBP": 119, "USP28": 119, "IL12A": 119, "RRAGC": 119, "ODC1": 119, "TEC": 119, "HOXA9": 119, "ACTN3": 119, "TIMP1": 119, "KCNIP2": 119, "KLF2": 119, "TAP1": 119, "RB1CC1": 119, "STMN2": 119, "POLD1": 119, "B2R8K8": 119, "PLCB1": 119, "CDC14A": 119, "MAGED1": 119, "DOK7": 119, "PDE3A": 119, "SIK3": 119, "E2F7": 119, "REST": 119, "GLMN": 119, "EFNB3": 119, "NFKBIE": 119, "MAP3K7": 119, "RSF1": 119, "HOXC6": 119, "DOK1": 119, "MYSM1": 119, "RASGRP3": 119, "PTPN5": 119, "UVRAG": 119, "CDCA3": 119, "FGF5": 119, "NPM1": 119, "ANGPT1": 119, "BRSK2": 120, "ANKRD2": 120, "C1S": 120, "VDAC1": 120, "DGKD": 120, "IRF2BP2": 120, "TBC1D10A": 120, "RITA1": 120, "TP53I3": 120, "RYR1": 120, "PAXIP1": 120, "BMF": 120, "RAB8A": 120, "MNX1": 120, "FANCE": 120, "OSTF1": 121, "UBLCP1": 121, "SSTR3": 121, "CETN2": 121, "ARHGAP24": 121, "STAT4": 121, "TNFRSF6B": 121, "PLP2": 121, "TRAF3IP2": 121, "Q4LE43": 121, "FZD5": 121, "RASSF1": 121, "TNFRSF11A": 121, "CSNK1E": 121, "FXN": 121, "COASY": 121, "PICK1": 121, "SUPT16H": 121, "CD58": 121, "SLC6A3": 121, "TFDP3": 121, "AANAT": 121, "AURKA": 121, "VPS28": 121, "CRP": 121, "EIF2AK2": 121, "MYO5A": 121, "CAMK1G": 121, "USP17L2": 122, "IRF7": 122, "TLR9": 122, "POPDC3": 122, "CMA1": 122, "RNF25": 122, "PPM1L": 122, "JMY": 122, "THOC5": 122, "ADRB1": 122, "GDF5": 122, "SEMA3F": 122, "PDLIM7": 122, "ARHGDIB": 122, "LILRB1": 122, "ATP2B1": 122, "RBBP8": 122, "TGFB2": 122, "NMBR": 122, "GNAI2": 123, "NFU1": 123, "CDK16": 123, "DYRK1A": 123, "Q59F04": 123, "OS9": 123, "CD79B": 123, "WNT16": 123, "EPHB4": 123, "CARD8": 123, "ABCC2": 123, "NEU1": 123, "P2RX7": 123, "PTK6": 123, "GFI1": 123, "TICAM1": 123, "OSM": 123, "PRSS21": 123, "ALOX5AP": 123, "NUSAP1": 123, "AKT2": 123, "STK3": 123, "CLIP1": 123, "PEA15": 123, "RPS27A": 123, "SPTB": 123, "ARHGEF1": 123, "ATP2B2": 123, "STUB1": 123, "PTH1R": 123, "EFNA2": 123, "RAPH1": 123, "CNKSR1": 123, "RECQL5": 123, "KPNA1": 123, "GLS2": 123, "SRI": 123, "CAMK1": 123, "FCER1A": 123, "C1R": 123, "PDCD1LG2": 123, "ERN2": 123, "PILRA": 123, "RAB11FIP5": 123, "DAAM1": 123, "GNRHR": 123, "AIMP1": 124, "ATG10": 124, "WDR83": 124, "MCPH1": 124, "DVL1": 124, "WWOX": 124, "SKAP1": 124, "TNFRSF8": 124, "SLC1A3": 124, "ING1": 124, "NSMAF": 124, "CD55": 124, "BIRC8": 124, "V9HWI5": 124, "TICAM2": 124, "SLA2": 124, "RALA": 124, "SPP1": 124, "TMED10": 124, "MARCH5": 124, "NEU3": 124, "PDZD2": 124, "APOBEC1": 124, "ING5": 124, "SMAD2": 124, "CIR1": 124, "SOX3": 124, "NMI": 124, "ASCC3": 124, "PARD6B": 124, "DPYD": 124, "MKNK2": 124, "MMP9": 124, "SPI1": 124, "CYBA": 124, "CREB3L2": 124, "ABCA1": 124, "DKK2": 124, "COL2A1": 124, "EPHA7": 124, "NTRK2": 124, "ANK1": 124, "HSPB8": 124, "KRT82": 124, "PRKD1": 124, "MX1": 124, "BID": 124, "KCNN1": 124, "BRE": 124, "KLC1": 124, "SLBP": 125, "GNB2": 125, "SEC63": 125, "B3KVH4": 125, "CCDC88A": 125, "POLR2E": 125, "ACTA2": 125, "CCL5": 125, "NUDT3": 125, "UNC5CL": 125, "HEXIM1": 125, "CDK2": 125, "IGF2": 125, "NEDD4L": 125, "NUAK2": 125, "CHAT": 125, "FGFR4": 125, "CCNB1": 125, "TRPC1": 125, "ZFYVE9": 125, "MAD2L1": 125, "IFIT1": 126, "ZNF10": 126, "BAG3": 126, "CREB3": 126, "IL15RA": 126, "HTR1A": 126, "CC2D1A": 126, "PRKCD": 126, "HOXB7": 126, "TLE2": 126, "CCKBR": 126, "POU2F2": 126, "UBE2R2": 126, "SLC22A8": 126, "SERPINF2": 126, "SLC6A1": 126, "BACH2": 126, "REN": 126, "RAD54L": 126, "DOC2A": 126, "USP24": 126, "FERMT2": 126, "NBN": 126, "ADAM15": 126, "HIPK4": 126, "INCENP": 126, "FPR2": 126, "PASK": 126, "LGR4": 126, "SELP": 126, "CARD11": 127, "GULP1": 127, "KIF1C": 127, "CBX1": 127, "TFRC": 127, "STON2": 127, "GNAI1": 127, "PKMYT1": 127, "PSENEN": 127, "DVL2": 127, "HSPA9": 127, "USP6": 127, "STK38L": 127, "CASP8AP2": 127, "ADAMTS4": 127, "RAD17": 127, "PPP2R4": 127, "EEF1B2": 127, "DHH": 127, "EIF3L": 127, "IKBKE": 127, "NFKBIZ": 127, "TDP2": 127, "MCF2L": 127, "RAB33B": 128, "ATG9A": 128, "NFATC3": 128, "CRHR1": 128, "DDB2": 128, "ATN1": 128, "CDK12": 128, "TUB": 128, "SLC29A1": 128, "EIF4EBP2": 128, "ADM2": 128, "PIRT": 128, "TIAM1": 128, "IL2RG": 128, "CBLB": 128, "MRGBP": 128, "NFAM1": 128, "UBE3A": 128, "PRKACA": 128, "IRF3": 128, "Q7Z322": 128, "HSPB2": 128, "RAB24": 128, "ARHGAP5": 128, "NOXA1": 128, "WNT10B": 128, "EIF4A2": 128, "EMSY": 128, "GTSE1": 128, "MBD3": 128, "POMC": 128, "AGRP": 128, "LTB4R": 128, "TPI1": 128, "RFC4": 129, "HMMR": 129, "AES": 129, "WSB1": 129, "ANGPT2": 129, "TGFBRAP1": 129, "PITX2": 129, "CCL3": 129, "CD274": 129, "WNK1": 129, "GTF2A1": 129, "USP9X": 129, "CTSD": 129, "PLSCR3": 129, "PLN": 129, "GPSM2": 129, "MAP2K1": 129, "DAB2IP": 129, "ANAPC7": 129, "LRP6": 129, "WNT5A": 129, "RAD9A": 129, "IL26": 129, "PPP2R5D": 129, "TRIM6": 129, "PRKAB1": 129, "BFAR": 129, "ADAP1": 129, "MARK3": 129, "VEGFB": 129, "SNAP29": 129, "TRIM33": 129, "KCNE1": 129, "BCAR1": 129, "LY9": 130, "TFAP2B": 130, "UBE2B": 130, "NACA": 130, "MEGF10": 130, "CACNA1E": 130, "CRTC3": 130, "IQGAP1": 130, "B0AZM9": 130, "HVCN1": 130, "ACTB": 130, "PAFAH1B1": 130, "PARP3": 130, "CENPJ": 130, "MOS": 130, "SH3GL2": 130, "FCGR2A": 130, "EHMT2": 130, "SUMO3": 130, "TMEM173": 130, "RIN1": 130, "PEG3": 130, "PPP1R15A": 130, "MKL2": 130, "CDK2AP1": 130, "GPKOW": 130, "SMG1": 130, "TACSTD2": 130, "KCNC4": 130, "CSF1R": 130, "WBP11": 130, "GCC1": 130, "ST13": 130, "MAP4K3": 130, "SMC6": 130, "TUBB": 131, "MPG": 131, "PPARGC1A": 131, "HDAC6": 131, "ITGAX": 131, "SEPT8": 131, "PTPRM": 131, "LGALS1": 131, "ABCB1": 131, "PDCD10": 131, "Q59FS6": 131, "NOX1": 131, "EIF3K": 131, "KLRC1": 131, "CCL20": 131, "HERC2": 131, "BTLA": 131, "C5AR1": 131, "DMC1": 131, "AOC1": 131, "NOTCH4": 131, "FGFR2": 131, "KRT6C": 131, "LIMK1": 131, "SPRY3": 131, "PPP1R2": 131, "HOOK3": 131, "PKN2": 131, "MS4A1": 131, "NRG2": 131, "LILRB2": 131, "ANKRD6": 131, "SERPINB2": 131, "USP3": 131, "ABL1": 131, "SFN": 131, "TSG101": 131, "LATS2": 131, "PVR": 132, "MPO": 132, "HOXA7": 132, "MAPK3": 132, "Q6MZW8": 132, "CCNE1": 132, "HIST2H3D": 132, "ALOX5": 132, "ZFYVE16": 132, "ADH4": 132, "LAMTOR3": 132, "EFNA1": 132, "CCK": 132, "TNFSF12": 132, "PML": 132, "RNF135": 132, "SF3B1": 132, "TCF12": 132, "MAML1": 132, "ACTR3B": 132, "CDC42BPB": 132, "RRAGB": 132, "PROK2": 132, "TASP1": 132, "FYB": 132, "DROSHA": 132, "ORC4": 132, "CHD4": 132, "BAG1": 132, "IP6K2": 132, "PRDM1": 132, "IREB2": 132, "PTPN7": 132, "B4DDH1": 132, "NTF4": 132, "PROKR2": 132, "CCDC80": 132, "CASP10": 132, "EIF4G2": 132, "MTMR4": 133, "TMSB4X": 133, "S100A10": 133, "TNFSF18": 133, "NRXN3": 133, "LEF1": 133, "RFC1": 133, "VAPA": 133, "C4B": 133, "SOX2": 133, "SMARCC1": 133, "PRKAR1B": 133, "ATG3": 133, "BCAP31": 133, "EIF2B4": 133, "BTG1": 133, "RGS18": 133, "PDCL": 133, "LGR5": 133, "SMG9": 133, "GRK7": 133, "EDAR": 133, "P4HA2": 133, "NTRK3": 133, "XDH": 133, "MRGPRX1": 133, "IL22": 133, "FES": 133, "CBL": 133, "NDE1": 133, "HIST1H2BD": 133, "DGKA": 133, "PRKAR2A": 134, "NR4A2": 134, "VASP": 134, "TNNI3": 134, "ING3": 134, "CASP14": 134, "CCNA1": 134, "HFE": 134, "BMPR1B": 134, "DUSP6": 134, "HDAC10": 134, "PDPK2P": 134, "PA2G4": 134, "HBA1": 134, "AAMP": 134, "STC2": 134, "FZD3": 134, "FZR1": 134, "DVL3": 134, "LRRK2": 134, "TPT1": 134, "BLM": 134, "PIKFYVE": 134, "MAP1LC3A": 134, "RSPO2": 134, "KDM3A": 134, "LDHC": 134, "PPP1R13L": 134, "RNF31": 134, "GSTA4": 134, "TNKS2": 134, "CKS1B": 134, "UTRN": 134, "FGF6": 134, "CABIN1": 134, "PARN": 134, "MCM5": 134, "CD86": 134, "BTG2": 134, "DZIP3": 134, "ADORA1": 134, "MTCH2": 135, "PPM1G": 135, "BGLAP": 135, "PIP5K1A": 135, "IMPDH2": 135, "Q59EA4": 135, "CLTCL1": 135, "TSGA10": 135, "LMO2": 135, "AHCYL1": 135, "IFNG": 135, "MARK1": 135, "GPS1": 135, "CSF1": 135, "RAB11FIP3": 135, "Q59FK4": 136, "IL33": 136, "TP53BP1": 136, "BUB3": 136, "UBE2D1": 136, "Q59HG2": 136, "PIK3R3": 136, "CASC5": 136, "KDM5C": 136, "PRMT6": 136, "STX5": 136, "P2RY4": 136, "TNF": 136, "RELA": 136, "TYRP1": 136, "AVPR2": 136, "FGF10": 136, "MAVS": 136, "USP8": 136, "SLA": 136, "MT-RNR2": 136, "NEDD1": 136, "GRIK2": 136, "SIRT7": 136, "TRAF7": 136, "TP53AIP1": 136, "FSCN1": 136, "MAPKAP1": 136, "SLC2A1": 136, "TTK": 136, "CCL18": 136, "GFI1B": 136, "TOP2A": 136, "CD28": 136, "PLEKHO1": 136, "CDC26": 136, "PKM": 136, "ANXA5": 136, "CBFA2T3": 137, "PIK3C3": 137, "PSME1": 137, "ITGB1BP2": 137, "TFF1": 137, "EEF1A2": 137, "PLAG1": 137, "PPP2R3A": 137, "RAD51": 137, "BEST1": 137, "CARD6": 137, "ISL1": 137, "UBE2O": 137, "SH3GL3": 137, "MPDZ": 137, "KCNJ1": 137, "SUPT5H": 137, "SUN2": 137, "HIST1H4C": 137, "ASAP1": 138, "HNF1A": 138, "GRIA1": 138, "KLK2": 138, "HDAC1": 138, "STK36": 138, "CRADD": 138, "PRRX1": 138, "CCR7": 138, "MSH3": 138, "GPRASP1": 138, "PSMB8": 138, "RAB5B": 138, "SAP30": 138, "NFX1": 138, "PELI1": 138, "CLDN7": 138, "PLXNB1": 138, "ARHGEF6": 138, "EFHC1": 138, "FOXO3": 138, "B3KP83": 138, "TOR1AIP1": 138, "ACAN": 138, "NPAT": 138, "TWIST1": 138, "ITGA5": 138, "PDGFRB": 138, "VEGFA": 138, "SMARCC2": 138, "GPC1": 138, "RUFY1": 138, "CASC3": 138, "RSPO3": 138, "TNFRSF25": 138, "ITM2B": 138, "WDR34": 138, "EPHB1": 138, "MAP3K6": 139, "TMPRSS2": 139, "STK38": 139, "FUNDC1": 139, "GORASP2": 139, "PIP4K2A": 139, "IL24": 139, "SNRPB": 139, "AATF": 139, "RAP2A": 139, "SIRT6": 139, "HIST1H2BM": 139, "SLC9A5": 139, "KCND3": 139, "POU2F1": 139, "EFNB2": 139, "SLC2A4RG": 139, "CEP85": 139, "CNPY3": 139, "FTH1": 139, "OGT": 139, "EIF4A1": 139, "CHMP4C": 139, "RIT1": 139, "MTSS1": 139, "GABBR1": 139, "EEF1D": 139, "VAMP1": 139, "NXPH1": 139, "H2AFX": 139, "GPER1": 139, "SYNJ2BP": 140, "COL5A2": 140, "PYGL": 140, "RBPJ": 140, "MMP26": 140, "BAZ1B": 140, "LRP5": 140, "TRIM56": 140, "SSTR4": 140, "TOP1": 140, "KRT18": 140, "KNG1": 140, "TAF15": 140, "DUSP13": 140, "CAT": 140, "STAP1": 140, "RBM39": 140, "GRIP1": 140, "ADA": 140, "RAP1GDS1": 141, "EPGN": 141, "RPL13A": 141, "IFNA5": 141, "TRIM23": 141, "CDC27": 141, "SMARCA5": 141, "ACACB": 141, "ZC3HC1": 141, "CHFR": 141, "ADIPOR1": 141, "ERCC3": 141, "CIB1": 141, "CALCB": 141, "BCL9": 141, "KCNQ4": 141, "MAD2L2": 141, "FLT3": 141, "ZYX": 141, "CUL4B": 141, "MAZ": 141, "CTSB": 141, "TBC1D7": 141, "MLST8": 141, "CRYBA2": 141, "TLR7": 141, "NSD1": 141, "CCR3": 141, "CTF1": 141, "STK11": 141, "DAB1": 141, "PTK2B": 141, "PTPRN": 141, "KIFC1": 141, "PPM1M": 141, "AGER": 141, "PTPRR": 141, "THBS1": 141, "PDE8A": 141, "CRYAA": 141, "ARF6": 141, "ULK1": 141, "TNK2": 141, "BACH1": 141, "YES1": 141, "RGCC": 141, "ITGA2B": 142, "PROKR1": 142, "AHSP": 142, "ATMIN": 142, "ATF6": 142, "RAPGEF2": 142, "MAPK14": 142, "MVP": 142, "ICK": 142, "KRT31": 142, "DUSP18": 142, "PTRF": 142, "TNFSF4": 142, "SSTR2": 142, "NRXN1": 142, "MYLK2": 142, "GRB14": 142, "NEFH": 142, "CCNH": 142, "BRD8": 142, "PRC1": 142, "PHGDH": 142, "RRAD": 142, "MAGEA11": 142, "CDC42BPA": 142, "GAD2": 142, "FBXW8": 142, "NDFIP2": 142, "DYNC1LI1": 142, "EIF2AK3": 142, "PAN3": 142, "STK26": 142, "B3KPF0": 142, "MYL9": 142, "HSPB6": 143, "DST": 143, "ANKHD1": 143, "KIF2B": 143, "CALR": 143, "CHIA": 143, "DNAJB1": 143, "CALB1": 143, "UBXN2B": 143, "CRIPT": 143, "COMMD1": 143, "PPP5C": 143, "PDHB": 143, "V9HWH0": 143, "UBC": 143, "UBR2": 143, "FBXO31": 143, "MUTYH": 143, "KLF6": 143, "SEMG2": 143, "KDM1B": 143, "DFFA": 143, "SH3BP5": 143, "STAM": 143, "IL18RAP": 143, "YEATS4": 143, "CDC25B": 143, "RALGAPA2": 143, "FN1": 143, "GLI3": 143, "FBXO4": 143, "MAP2K2": 143, "HIST3H3": 143, "FREM1": 143, "BCKDK": 143, "CDK14": 144, "AP2S1": 144, "EIF3J": 144, "USP2": 144, "HSPA2": 144, "CGN": 144, "PTN": 144, "SH3BP2": 144, "SNX6": 144, "SIX3": 144, "SAT1": 144, "RCAN1": 144, "RBP1": 144, "MORC2": 144, "EPB42": 144, "POLB": 144, "ID2": 144, "NUMBL": 144, "IKBIP": 144, "SHROOM3": 144, "KDM2B": 144, "CD244": 144, "NCR1": 144, "EIF3G": 144, "RARB": 144, "MAPK8": 144, "SASH3": 144, "EIF3H": 144, "CYLD": 144, "ZMYND11": 144, "LAT": 144, "ERBB3": 144, "KDELR1": 144, "GAB2": 144, "APOE": 144, "B2RAH2": 144, "BRCA2": 144, "TUBB4A": 144, "MARCO": 145, "YWHAH": 145, "GPR37L1": 145, "ENPEP": 145, "NCOA4": 145, "CDKN1B": 145, "SIKE1": 145, "ANXA1": 145, "KTN1": 145, "ATP2B4": 145, "ALYREF": 145, "MYCN": 145, "TAP2": 145, "WASL": 145, "TUBB2A": 146, "DEFA5": 146, "PRNP": 146, "ZFYVE28": 146, "SPEN": 146, "MIB1": 146, "MAX": 146, "MOB1B": 146, "B3KXA2": 146, "UPF2": 146, "PDGFD": 146, "PPM1D": 146, "CASP5": 146, "APC2": 146, "SLIT2": 146, "SOCS3": 146, "FEZ2": 146, "CDCA7": 146, "IL6": 147, "SNAPIN": 147, "GFPT2": 147, "FAN1": 147, "CYP2C9": 147, "DLG4": 147, "CTSH": 147, "RALBP1": 147, "MINA": 147, "NCBP1": 147, "MMP3": 147, "IRF9": 147, "HIST1H1A": 147, "LILRB4": 147, "B2RAH5": 147, "NOX5": 147, "RMI1": 147, "TEK": 148, "MAOA": 148, "PSMD6": 148, "CTDSP2": 148, "EGLN1": 148, "TBCB": 148, "CGA": 148, "STK24": 148, "Q53G95": 148, "LPAR2": 148, "OPRL1": 148, "CNTROB": 148, "GTF2F1": 148, "SLAMF1": 148, "TNIK": 148, "PAX9": 148, "MPZL1": 148, "PSMC2": 148, "KCNK3": 148, "SOCS7": 148, "TUBB4B": 148, "PNPT1": 148, "F7": 148, "TNFRSF21": 148, "POU5F1": 148, "ACTR3": 148, "ACIN1": 148, "WNT8A": 148, "CRYGB": 148, "RASSF7": 148, "PAH": 148, "DACT1": 148, "SPARC": 148, "CDC37": 148, "CASP12": 148, "DNMT1": 149, "NOTCH3": 149, "FZD4": 149, "CXCL9": 149, "SORL1": 149, "LIFR": 149, "GADD45G": 149, "SVIL": 149, "SP1": 149, "ING2": 149, "RFXANK": 149, "ADAMTS13": 149, "DAZAP1": 149, "ID1": 149, "TP53": 149, "ACKR4": 149, "ATP2A2": 149, "CCNE2": 149, "CNR2": 149, "LAMB3": 149, "CCND1": 149, "A0A024R693": 149, "IL10RB": 149, "CCL13": 149, "RBL2": 149, "PTPN18": 149, "TAF7": 149, "SEC14L1": 149, "CAV2": 149, "CHD1L": 149, "GGA1": 149, "STIP1": 149, "APP": 149, "ENOX2": 149, "GABARAP": 149, "RAPGEF5": 149, "Q59F12": 149, "THEM4": 149, "KLF5": 149, "BIRC6": 149, "PHLPP1": 149, "PPP1R12C": 149, "RAB11FIP2": 149, "HSP90AA1": 149, "VLDLR": 149, "IL10RA": 149, "PVRL2": 149, "HDAC2": 149, "ROS1": 150, "PCOLCE": 150, "KCNJ3": 150, "SPSB1": 150, "IRF1": 150, "NEFL": 150, "GATA1": 150, "KCTD11": 150, "TAX1BP3": 150, "KIZ": 150, "KLF1": 150, "NR5A2": 150, "DNAJC9": 150, "TRAF5": 150, "VMP1": 150, "P2RY1": 150, "ANAPC1": 150, "AFAP1": 150, "HDAC9": 150, "SH2D1A": 151, "SLC2A4": 151, "ABI1": 151, "NGFRAP1": 151, "RNPS1": 151, "APPL2": 151, "RAPGEF1": 151, "CX3CR1": 151, "MYL5": 151, "CBLL1": 151, "SRSF1": 151, "STXBP2": 151, "TIMP3": 151, "XAB2": 151, "MLXIPL": 151, "PDCD4": 151, "GATA6": 151, "B3KT21": 151, "HNRNPK": 151, "LASP1": 151, "AREGB": 151, "SAFB": 151, "HIST3H2BB": 151, "ATG5": 151, "TACC2": 151, "SNCA": 151, "RFX1": 151, "PPP6C": 151, "TIPRL": 151, "RPS6KA6": 151, "GRB7": 151, "COL17A1": 151, "PRKAG1": 151, "KLF13": 151, "IFNA8": 151, "CASR": 152, "ICOSLG": 152, "BNIP3L": 152, "CSNK1A1L": 152, "MBTPS2": 152, "PPP1R3C": 152, "RPS6KB1": 152, "UBL5": 152, "WNT2": 152, "KCNA5": 152, "ELOVL1": 152, "PGAM1": 152, "PKD2L1": 152, "NHLRC1": 152, "MFN1": 152, "RPLP2": 152, "LIMS1": 152, "TIRAP": 152, "FMNL2": 152, "LTB": 152, "RRM2": 152, "WNT2B": 152, "CMTM3": 152, "CCR6": 152, "SERPINA5": 152, "HIST1H2BH": 152, "GGCX": 152, "VIM": 152, "CKS2": 152, "CMKLR1": 152, "DUOX2": 152, "MYOM2": 152, "UBE2L6": 152, "DPY30": 152, "MAPK9": 152, "ZBP1": 152, "IRS2": 152, "PSMD4": 152, "SEC16A": 153, "E2F3": 153, "TP53RK": 153, "AURKB": 153, "WT1": 153, "PAK2": 153, "MID1": 153, "TLK2": 153, "DACH1": 153, "CDH5": 153, "NR1D2": 153, "GJB6": 153, "DLGAP2": 153, "CCL17": 153, "TPH1": 153, "TRIM24": 153, "LHX4": 153, "ITM2C": 153, "ELMO1": 153, "NLRP4": 153, "ZBTB33": 153, "AGTR2": 153, "GRIA4": 153, "ZNF652": 153, "SCAMP3": 154, "SKAP2": 154, "CD40LG": 154, "LMO4": 154, "CNR1": 154, "FOXA2": 154, "DAPP1": 154, "ARHGAP22": 154, "RIPK2": 154, "ASIC1": 154, "GNG2": 154, "SF3B4": 154, "MYCBP2": 154, "MYT1": 154, "DUSP19": 154, "RRAGA": 154, "TPM1": 154, "ADH1A": 154, "NSF": 154, "RUFY2": 154, "PSMC6": 154, "MAML3": 154, "AIFM1": 154, "FPR3": 154, "HES6": 154, "BACE1": 154, "SYK": 154, "PHB": 154, "SDC2": 154, "ISCU": 154, "MYOCD": 154, "LAMC1": 154, "RAG2": 154, "GLI1": 154, "IRAK4": 154, "HEY2": 154, "MYL4": 154, "BIRC7": 154, "ANKRD28": 154, "Q9BSK3": 154, "ANP32B": 155, "RMI2": 155, "ARHGAP35": 155, "UNC5B": 155, "CENPE": 155, "AGA": 155, "NLRP3": 155, "ARHGDIA": 155, "AP2B1": 155, "GFPT1": 155, "SIK2": 155, "ADCY2": 155, "IRF2BP1": 155, "ITGB5": 156, "PDCD2": 156, "EDARADD": 156, "CCNA2": 156, "INS": 156, "PVRL3": 156, "TRIP6": 156, "GSPT1": 156, "SLC10A1": 156, "RIT2": 156, "TAF12": 156, "PCSK1": 156, "MLLT4": 156, "NFE2L2": 156, "SPRY4": 156, "PDK1": 156, "ROBO3": 156, "FAAP24": 156, "Q8WYR3": 156, "MYF5": 156, "ADAM10": 156, "DGKZ": 156, "TLR6": 156, "NR1H4": 156, "SLC6A12": 156, "ITGB1BP1": 156, "DUOX1": 156, "CD300LB": 156, "CHKA": 156, "SUV420H1": 156, "CORO1B": 156, "SRCIN1": 156, "IGFBP1": 156, "MAP4": 156, "FUS": 156, "RXRG": 156, "SYN1": 156, "POU4F1": 156, "KCNH2": 156, "SEMA3A": 156, "HSPB1": 156, "ITGAE": 156, "GNG3": 157, "PREX1": 157, "CDK9": 157, "EPHA4": 157, "NCF1": 157, "ARHGEF11": 157, "ITGA1": 157, "F11R": 157, "KPNA3": 157, "POLH": 157, "GJB2": 157, "MBL2": 157, "NUP133": 157, "BCL2L1": 157, "CACNB2": 157, "RBX1": 157, "RPA3": 157, "CTSV": 157, "CD46": 157, "LAMA2": 157, "PBRM1": 157, "AP1B1": 157, "JPH2": 157, "SSH1": 157, "KCNJ4": 157, "PIK3CA": 157, "RAC1": 157, "LIG1": 157, "ZIC3": 157, "NF2": 158, "CGGBP1": 158, "DOK3": 158, "SCN5A": 158, "SELPLG": 158, "HOXB6": 158, "EPRS": 158, "NR1I2": 158, "TUBG1": 158, "SLC4A4": 158, "CTNNAL1": 158, "TPX2": 158, "EIF3A": 158, "DUSP1": 158, "TIE1": 158, "KATNA1": 159, "SYNGAP1": 159, "SASH1": 159, "GNB1": 159, "SFPQ": 159, "NOL3": 159, "ADCY5": 159, "PPP3CB": 159, "SOST": 159, "ZNF24": 159, "HIPK2": 159, "KPNA6": 159, "PRDM2": 159, "NCSTN": 159, "GJA1": 159, "TBC1D1": 159, "MTNR1A": 159, "TUBA3E": 159, "PRCC": 159, "RAD23B": 159, "RHOA": 159, "MEP1B": 159, "RILPL2": 159, "AMIGO2": 159, "LPAR3": 159, "DLL3": 159, "RUNX1": 159, "NFIL3": 159, "PARD3": 159, "FEZ1": 159, "MXD1": 159, "DHX36": 159, "PAG1": 159, "SELL": 159, "BTF3": 159, "WNT9A": 159, "AP4B1": 160, "EIF2B3": 160, "A0A024RDL4": 160, "CTDNEP1": 160, "GLRB": 160, "PLXNA2": 160, "GADD45A": 160, "KMT2B": 160, "USP16": 160, "EVL": 160, "NUP50": 160, "GRK5": 160, "TIA1": 160, "Q8NFJ4": 160, "DMTN": 160, "TRIM32": 160, "ISG20": 160, "MAP3K2": 160, "PTPRA": 160}